{"dokumentstatus":{"dokument":{"hangar_id":"5206282","dok_id":"HB01SkU25","rm":"2023/24","beteckning":"SkU25","typ":"bet","subtyp":"bet","doktyp":"bet","typrubrik":"Betänkande 2023/24:SkU25","dokumentnamn":"Betänkande","debattnamn":"Debatt om förslag","tempbeteckning":null,"organ":"SkU","mottagare":null,"nummer":"25","slutnummer":"0","datum":"2024-04-22 00:00:00","systemdatum":"2024-05-23 09:27:41","publicerad":"2024-04-22 07:18:57","titel":"Ny tullbefogenhetslag","subtitel":null,"status":"planerat","htmlformat":null,"relaterat_id":null,"source":"Brus","sourceid":"967caf3b-dd8d-41e2-ad63-7cb2fff9f071","metadata":null,"dokument_url_text":"https://data.riksdagen.se/dokument/HB01SkU25/text","dokument_url_html":"https://data.riksdagen.se/dokument/HB01SkU25","dokumentstatus_url_xml":"https://data.riksdagen.se/dokumentstatus/HB01SkU25","utskottsforslag_url_xml":"https://data.riksdagen.se/utskottsforslag/HB01SkU25","html":"<h2>Ny tullbefogenhetslag</h2>\r\nDokumentet är inte publicerat"},"dokaktivitet":{"aktivitet":[{"kod":"UBE","namn":"Beredning","datum":"2024-05-30 00:00:00","status":"inträffat","ordning":"0","process":null},{"kod":"UBE","namn":"Beredning","datum":"2024-09-17 00:00:00","status":"planerat","ordning":"0","process":null},{"kod":"JUS","namn":"Justering","datum":"2024-09-26 00:00:00","status":"planerat","ordning":"0","process":null},{"kod":"TRY","namn":"Trycklov","datum":"2024-09-27 00:00:00","status":"planerat","ordning":"0","process":null},{"kod":"B","namn":"Bordläggning","datum":"2024-10-01 00:00:00","status":"planerat","ordning":"0","process":null},{"kod":"BEH","namn":"Behandling","datum":"2024-10-02 00:00:00","status":"planerat","ordning":"0","process":null},{"kod":"BES","namn":"Beslut","datum":"2024-10-02 00:00:00","status":"planerat","ordning":"0","process":null}]},"dokuppgift":{"uppgift":{"kod":"statustext","namn":"statustext","text":"Utskottet arbetar med ärendet","dok_id":"HB01SkU25","systemdatum":"2024-05-31 00:35:36"}},"dokreferens":{"referens":{"referenstyp":"behandlar","uppgift":"Proposition 2023/24:132 Ny tullbefogenhetslag","ref_dok_id":"HB03132","ref_dok_typ":"prop","ref_dok_rm":"2023/24","ref_dok_bet":"132","ref_dok_titel":"Ny tullbefogenhetslag","ref_dok_subtitel":null,"ref_dok_subtyp":"prop","ref_dok_dokumentnamn":"Proposition"}}}}