{"dokumentstatus":{"dokument":{"hangar_id":"5198033","dok_id":"HB01NU20","rm":"2023/24","beteckning":"NU20","typ":"bet","subtyp":"utl","doktyp":"bet","typrubrik":"Utlåtande 2023/24:NU20","dokumentnamn":"Utlåtande","debattnamn":"Debatt om förslag","tempbeteckning":null,"organ":"NU","mottagare":null,"nummer":"20","slutnummer":"0","datum":"2024-05-16 00:00:00","systemdatum":"2024-06-25 11:30:45","publicerad":"2024-04-02 11:30:04","titel":"Kommissionens vitbok om utgående investeringar","subtitel":null,"status":"Webbpublicering","htmlformat":"html","relaterat_id":null,"source":"RIM","sourceid":"7636753f-a9b3-4cc1-ad0e-e7034b94e94d","metadata":null,"dokument_url_text":"https://data.riksdagen.se/dokument/HB01NU20/text","dokument_url_html":"https://data.riksdagen.se/dokument/HB01NU20","dokumentstatus_url_xml":"https://data.riksdagen.se/dokumentstatus/HB01NU20","utskottsforslag_url_xml":"https://data.riksdagen.se/utskottsforslag/HB01NU20","html":"<style><!--\r\n .w600px{width: 600px;font-family:Verdana, Geneva, sans-serif}\r\nh2.dtyp{font-size:1.5em !important;} \r\n@page Section1 { size:467.8pt 686.05pt; margin:45.35pt 102.05pt 73.7pt 70.85pt }\r\ndiv.Section1 { page:Section1 }\r\nzbody { text-align:justify; line-height:12.5pt; font-family:'Verdana'; font-size:9.5pt }\r\nzh1, h2, h3, h4, h5, h6, p { margin:3.1pt 0pt 0pt }\r\nzli, table { margin-top:3.1pt; margin-bottom:0pt }\r\nzh1 { margin-top:3.1pt; margin-bottom:12pt; text-align:left; page-break-inside:auto; page-break-after:avoid; line-height:12.5pt; font-family:'Verdana'; font-size:16pt; font-weight:normal; color:#000000 }\r\nzh2 { margin-top:20pt; margin-bottom:6pt; text-align:left; page-break-inside:avoid; page-break-after:avoid; line-height:12.5pt; font-family:'Verdana'; font-size:13.5pt; font-weight:normal; color:#000000 }\r\nzh3 { margin-top:20pt; margin-bottom:3.1pt; text-align:left; page-break-inside:avoid; page-break-after:avoid; line-height:12.5pt; font-family:'Verdana'; font-size:10.5pt; font-weight:bold; color:#000000 }\r\nzh4 { margin-top:15pt; margin-bottom:3.1pt; text-align:left; page-break-inside:avoid; page-break-after:avoid; line-height:12.5pt; font-family:'Verdana'; font-size:10.5pt; font-weight:normal; font-style:italic; color:#000000 }\r\nzh5 { margin-top:6.25pt; margin-bottom:0pt; text-align:left; page-break-inside:avoid; page-break-after:avoid; line-height:12.5pt; font-family:'Verdana'; font-size:9.5pt; font-weight:bold; color:#000000 }\r\nzh6 { margin-top:6.25pt; margin-bottom:0pt; text-align:left; page-break-inside:avoid; page-break-after:avoid; line-height:12.5pt; font-family:'Verdana'; font-size:9.5pt; font-weight:normal; font-style:italic; color:#000000 }\r\n.Heading7 { margin-top:2pt; margin-bottom:0pt; text-align:left; page-break-inside:avoid; page-break-after:avoid; line-height:12.5pt; font-family:'Verdana'; font-size:9.5pt; font-weight:normal; font-style:italic; color:#243f60; -aw-style-name:heading7 }\r\n.Heading8 { margin-top:2pt; margin-bottom:0pt; text-align:left; page-break-inside:avoid; page-break-after:avoid; line-height:12.5pt; font-family:'Verdana'; font-size:9pt; font-weight:normal; color:#272727; -aw-style-name:heading8 }\r\n.Heading9 { margin-top:2pt; margin-bottom:0pt; text-align:left; page-break-inside:avoid; page-break-after:avoid; line-height:12.5pt; font-family:'Verdana'; font-size:9pt; font-weight:normal; font-style:italic; color:#272727; -aw-style-name:heading9 }\r\n.Avsnittsrubrik { margin-top:0pt; margin-bottom:27.7pt; text-align:left; page-break-before:always; page-break-after:avoid; line-height:normal; font-family:'Verdana'; font-size:16pt }\r\n.Avvikandemeningrubrik { margin-top:0pt; margin-bottom:3.1pt; text-align:left; page-break-inside:avoid; page-break-after:avoid; line-height:12.5pt; font-family:'Verdana'; font-size:10.5pt; font-weight:bold }\r\n.BalloonText { margin-top:3.1pt; margin-bottom:0pt; text-align:justify; line-height:normal; font-family:Tahoma; font-size:8pt }\r\n.Bilaga { margin-top:0pt; margin-bottom:0pt; text-align:left; page-break-before:always; page-break-after:avoid; line-height:normal; widows:0; orphans:0; font-family:'Verdana'; font-size:8pt; font-variant:small-caps; text-decoration:underline }\r\n.Bilagerubrik { margin-top:0pt; margin-bottom:17.7pt; text-align:left; page-break-after:auto; line-height:normal; widows:0; orphans:0; font-family:'Verdana'; font-size:16pt }\r\n.Bild-Rubrik { margin-top:8pt; margin-bottom:0pt; text-align:left; page-break-inside:avoid; page-break-after:avoid; line-height:10pt; font-family:'Verdana'; font-size:9.5pt; font-weight:bold }\r\n.Bild-Underrubrik { margin-top:0pt; margin-bottom:1pt; text-align:left; page-break-inside:avoid; page-break-after:avoid; line-height:8pt; font-family:'Verdana'; font-size:8pt; font-weight:normal; font-style:italic }\r\n.BodyText { margin-top:3.1pt; margin-bottom:0pt; text-align:left; line-height:12.5pt; font-family:'Verdana'; font-size:9.5pt }\r\n.BodyTextIndent2 { margin-top:3.1pt; margin-left:14.15pt; margin-bottom:6pt; text-align:justify; line-height:200%; font-family:'Verdana'; font-size:9.5pt }\r\n.Citatindrag { margin-top:0pt; margin-left:14.2pt; margin-bottom:6.1pt; text-indent:14.2pt; text-align:justify; line-height:10pt; font-family:'Verdana'; font-size:9.5pt }\r\n.CommentText { margin-top:3.1pt; margin-bottom:0pt; text-align:justify; line-height:normal; font-family:'Verdana'; font-size:10pt }\r\n.Deltagare { margin-top:0pt; margin-bottom:0pt; text-align:justify; page-break-inside:avoid; page-break-after:avoid; line-height:9.5pt; font-family:'Verdana'; font-size:9.5pt }\r\n.Diagram-Rubrik { margin-top:8pt; margin-bottom:0pt; text-align:left; page-break-inside:avoid; page-break-after:avoid; line-height:10pt; font-family:'Verdana'; font-size:9.5pt; font-weight:bold }\r\n.Diagram-Underrubrik { margin-top:0pt; margin-bottom:1pt; text-align:left; page-break-inside:avoid; page-break-after:avoid; line-height:8pt; font-family:'Verdana'; font-size:8pt; font-weight:normal; font-style:italic }\r\n.DokumentRubrik { margin-top:6pt; margin-bottom:24pt; text-align:left; line-height:normal; border-bottom:0.75pt solid #000000; padding-bottom:4pt; font-family:'Verdana'; font-size:18pt; -aw-border-bottom:0.5pt single }\r\n.Dokumentbeteckning { margin-top:0pt; margin-bottom:0pt; text-align:left; page-break-inside:avoid; page-break-after:avoid; line-height:12.5pt; font-family:'Verdana'; font-size:16pt }\r\n.Fluglort { margin-top:0.1pt; margin-bottom:0pt; text-align:justify; line-height:0.7pt; font-family:'Verdana'; font-size:9.5pt }\r\n.Footer { margin-top:3.1pt; margin-bottom:0pt; text-align:justify; line-height:normal; font-family:'Verdana'; font-size:9.5pt }\r\n.FootnoteText { margin-top:0pt; margin-bottom:0pt; text-align:justify; line-height:8pt; font-family:'Verdana'; font-size:8pt }\r\n.Fotnotstextindrag { margin-top:0pt; margin-left:5.65pt; margin-bottom:0pt; text-align:left; line-height:8pt; font-family:'Verdana'; font-size:8pt }\r\n.Frslagspunkt { margin-top:0pt; margin-bottom:0pt; text-align:left; page-break-inside:avoid; page-break-after:avoid; line-height:12.5pt; font-family:'Verdana'; font-size:9.5pt; font-weight:bold }\r\n.Frslagstext { margin-top:0pt; margin-bottom:0pt; text-align:justify; line-height:12.5pt; font-family:'Verdana'; font-size:9.5pt }\r\n.Frteckningsrubrik { margin-top:9.6pt; margin-bottom:3.1pt; text-align:left; page-break-inside:avoid; page-break-after:avoid; line-height:normal; font-family:'Verdana'; font-size:9.5pt; font-weight:normal; font-style:italic; color:#000000 }\r\n.Grupprubrik { margin-top:6pt; margin-bottom:0pt; text-align:left; page-break-inside:avoid; page-break-after:avoid; line-height:12.5pt; font-family:'Verdana'; font-size:9.5pt; font-style:italic }\r\n.Grupprubrikindrag { margin-top:6pt; margin-left:22.1pt; margin-bottom:0pt; text-align:left; page-break-inside:avoid; page-break-after:avoid; line-height:12.5pt; font-family:'Verdana'; font-size:9.5pt; font-style:italic }\r\n.Header { margin-top:0pt; margin-bottom:0pt; text-align:justify; line-height:normal; font-family:'Verdana'; font-size:7.5pt; font-variant:small-caps }\r\n.Innehllsfrteckning { margin-top:0pt; margin-bottom:17.7pt; text-align:left; page-break-before:always; page-break-after:auto; line-height:normal; font-family:'Verdana'; font-size:16pt }\r\n.Kanslikommentar { margin-top:3.1pt; margin-bottom:12pt; text-align:left; page-break-after:avoid; line-height:12.5pt; font-family:'Verdana'; font-size:16pt }\r\n.Kantrubrik { margin-top:0pt; margin-bottom:0pt; text-align:justify; line-height:normal; font-family:'Verdana'; font-size:7.5pt }\r\n.ListBullet { margin-top:6.25pt; margin-left:17.85pt; margin-bottom:6.25pt; text-indent:-17.85pt; text-align:justify; line-height:12.5pt; font-family:'Verdana'; font-size:9.5pt }\r\n.ListParagraph { margin-top:3.1pt; margin-left:28.35pt; margin-bottom:0pt; text-align:justify; line-height:12.5pt; font-family:'Verdana'; font-size:9.5pt }\r\n.Litentext { margin-top:0pt; margin-bottom:0pt; text-align:justify; line-height:normal; font-family:'Verdana'; font-size:8pt }\r\n.Mellanrubrik { margin-top:11pt; margin-bottom:3.1pt; text-align:left; page-break-after:avoid; line-height:12.5pt; font-family:'Verdana'; font-size:9.5pt; font-style:italic }\r\n.Mellanrum { margin-top:0pt; margin-bottom:0pt; text-align:left; page-break-before:auto; page-break-after:auto; line-height:1pt; widows:0; orphans:0; font-family:'Verdana'; font-size:1pt; font-variant:small-caps; text-decoration:none; color:#ffffff }\r\n.NormalIndent { margin-top:0pt; margin-bottom:0pt; text-indent:11.35pt; text-align:justify; line-height:12.5pt; font-family:'Verdana'; font-size:9.5pt }\r\n.Normalinskjuten { margin-top:0pt; margin-left:22.1pt; margin-bottom:0pt; text-align:justify; line-height:12.5pt; font-family:'Verdana'; font-size:9.5pt }\r\n.Normalinskjutenindrag { margin-top:0pt; margin-left:22.1pt; margin-bottom:0pt; text-indent:11.35pt; text-align:justify; line-height:12.5pt; font-family:'Verdana'; font-size:9.5pt }\r\n.Normalinskjutenkursiv { margin-top:6pt; margin-bottom:0pt; line-height:normal; font-family:'Verdana'; font-size:10pt; font-style:italic }\r\n.Normalkursiv { margin-top:3.1pt; margin-bottom:0pt; text-align:left; line-height:12.5pt; font-family:'Verdana'; font-size:9.5pt; font-style:italic }\r\n.Normalruta { margin:3.1pt 5.65pt 0pt; text-align:justify; page-break-inside:avoid; page-break-after:avoid; line-height:12.5pt; border:0.75pt solid #000000; padding:4pt; font-family:'Verdana'; font-size:10.5pt; -aw-border:0.5pt single }\r\n.Normalrutafet { margin:3.1pt 5.65pt 0pt; text-align:justify; page-break-inside:avoid; page-break-after:avoid; line-height:12.5pt; border:0.75pt solid #000000; padding:4pt; font-family:'Verdana'; font-size:10.5pt; font-weight:bold; -aw-border:0.5pt single }\r\n.Normalrutaindrag { margin:0pt 5.65pt; text-indent:11.35pt; text-align:justify; page-break-inside:avoid; page-break-after:avoid; line-height:12.5pt; border:0.75pt solid #000000; padding:4pt; font-family:'Verdana'; font-size:10.5pt; -aw-border:0.5pt single }\r\n.Normalutanluftfre { margin-top:0pt; margin-bottom:0pt; text-align:justify; line-height:12.5pt; font-family:'Verdana'; font-size:9.5pt }\r\n.NormalNoll { margin-top:0pt; margin-bottom:3.1pt; text-align:left; line-height:12.5pt; font-family:'Verdana'; font-size:10.5pt; font-weight:bold }\r\n.NumlistaTOC { margin:3.1pt 28.35pt 0pt 0pt; text-indent:0pt; text-align:left; line-height:normal; font-family:'Verdana'; font-size:9.5pt }\r\n.Ordfranden { margin-top:3.1pt; margin-bottom:22pt; text-align:left; page-break-inside:avoid; page-break-after:avoid; line-height:normal; font-family:'Verdana'; font-size:9.5pt; font-style:italic }\r\n.OrtochDatum { margin-top:18pt; margin-bottom:18pt; text-align:left; page-break-inside:avoid; page-break-after:avoid; line-height:normal; font-family:'Verdana'; font-size:9.5pt }\r\n.Punktlistabomb { margin-top:6.25pt; margin-left:14.2pt; margin-bottom:6.25pt; text-indent:-14.2pt; text-align:justify; line-height:12.5pt; font-family:'Verdana'; font-size:9.5pt }\r\n.Punktlistagemener { margin-top:6.25pt; margin-left:14.2pt; margin-bottom:6.25pt; text-indent:-14.2pt; text-align:justify; line-height:12.5pt; font-family:'Verdana'; font-size:9.5pt }\r\n.Punktlistalinje { margin-top:6.25pt; margin-left:14.2pt; margin-bottom:6.25pt; text-indent:-14.2pt; text-align:justify; line-height:12.5pt; font-family:'Verdana'; font-size:9.5pt }\r\n.Punktlistasiffra { margin-top:6.25pt; margin-left:14.2pt; margin-bottom:6.25pt; text-indent:-14.2pt; text-align:justify; line-height:12.5pt; font-family:'Verdana'; font-size:9.5pt }\r\n.PVgnar { margin-top:3.1pt; margin-bottom:26pt; text-align:left; page-break-inside:avoid; page-break-after:avoid; line-height:normal; font-family:'Verdana'; font-size:9.5pt }\r\n.Quote { margin-top:6.1pt; margin-left:14.2pt; margin-bottom:0pt; text-align:justify; line-height:10pt; font-family:'Verdana'; font-size:9.5pt }\r\n.R1 { margin-top:3.1pt; margin-bottom:12pt; text-align:left; page-break-after:avoid; line-height:12.5pt; font-family:'Verdana'; font-size:16pt }\r\n.R1bilaga { margin-top:3.1pt; margin-bottom:12pt; text-align:left; page-break-after:auto; line-height:12.5pt; font-family:'Verdana'; font-size:16pt }\r\n.R2 { margin-top:20pt; margin-bottom:6pt; text-align:left; page-break-inside:avoid; page-break-after:avoid; line-height:12.5pt; font-family:'Verdana'; font-size:13.5pt }\r\n.R3 { margin-top:20pt; margin-bottom:3.1pt; text-align:left; page-break-inside:avoid; page-break-after:avoid; line-height:12.5pt; font-family:'Verdana'; font-size:10.5pt; font-weight:bold }\r\n.R4 { margin-top:15pt; margin-bottom:3.1pt; text-align:left; page-break-inside:avoid; page-break-after:avoid; line-height:12.5pt; font-family:'Verdana'; font-size:10.5pt; font-weight:normal; font-style:italic; color:#000000 }\r\n.R5 { margin-top:6.25pt; margin-bottom:0pt; text-align:left; page-break-inside:avoid; page-break-after:avoid; line-height:12.5pt; font-family:'Verdana'; font-size:9.5pt; font-weight:bold }\r\n.R6 { margin-top:6.25pt; margin-bottom:0pt; text-align:left; page-break-inside:avoid; page-break-after:avoid; line-height:12.5pt; font-family:'Verdana'; font-size:9.5pt; font-weight:normal; font-style:italic; color:#000000 }\r\n.Reservationshnvisning { margin-top:0pt; margin-bottom:8pt; text-align:right; line-height:12.5pt; font-family:'Verdana'; font-size:9.5pt; font-style:italic }\r\n.Reservationsrubrik { margin-top:0pt; margin-bottom:3.1pt; text-align:left; page-break-inside:avoid; page-break-after:avoid; line-height:12.5pt; font-family:'Verdana'; font-size:10.5pt; font-weight:bold }\r\n.Rubrik1Dokumentinformation { margin-top:0pt; margin-bottom:0pt; text-align:left; page-break-inside:avoid; page-break-after:avoid; line-height:12.5pt; font-family:'Verdana'; font-size:16pt }\r\n.Rubrik1bilaga { margin-top:0pt; margin-bottom:27.7pt; text-align:left; page-break-after:auto; line-height:12.5pt; font-family:'Verdana'; font-size:16pt }\r\n.Rubrik1medsidhuvud { margin-top:3.1pt; margin-bottom:12pt; text-align:left; page-break-before:always; page-break-after:avoid; line-height:12.5pt; font-family:'Verdana'; font-size:16pt }\r\n.Rubrik1numrerat { margin-top:3.1pt; margin-left:0pt; margin-bottom:12pt; text-indent:0pt; text-align:left; page-break-after:avoid; line-height:12.5pt; font-family:'Verdana'; font-size:16pt }\r\n.Rubrik1numreratmedsidhuvud { margin-top:0pt; margin-left:0pt; margin-bottom:16pt; text-indent:0pt; text-align:left; page-break-before:always; page-break-after:avoid; line-height:normal; font-family:'Verdana'; font-size:16pt }\r\n.Rubrik2bilaga { margin-top:20pt; margin-bottom:6pt; text-align:left; page-break-inside:avoid; page-break-after:avoid; line-height:12.5pt; font-family:'Verdana'; font-size:13.5pt }\r\n.Rubrik2numrerat { margin-top:20pt; margin-left:0pt; margin-bottom:6pt; text-indent:0pt; text-align:left; page-break-inside:avoid; page-break-after:avoid; line-height:12.5pt; font-family:'Verdana'; font-size:13.5pt }\r\n.Rubrik3numrerat { margin-top:20pt; margin-left:0pt; margin-bottom:3.1pt; text-indent:0pt; text-align:left; page-break-inside:avoid; page-break-after:avoid; line-height:12.5pt; font-family:'Verdana'; font-size:10.5pt; font-weight:bold }\r\n.Sammanfattning { margin-top:3.1pt; margin-bottom:12pt; text-align:left; page-break-after:auto; line-height:12.5pt; font-family:'Verdana'; font-size:16pt }\r\n.Sidhuvudhgerstlld { margin-top:0pt; margin-bottom:0pt; text-align:right; line-height:normal; font-family:'Verdana'; font-size:7.5pt; font-variant:small-caps }\r\n.Sidhuvudvnsterstlld { margin-top:0pt; margin-bottom:0pt; text-align:left; line-height:normal; font-family:'Verdana'; font-size:7.5pt; font-variant:small-caps }\r\n.Stdrubrik { margin-top:12pt; margin-bottom:0pt; line-height:12pt; font-family:'Verdana'; font-size:9.5pt; font-weight:bold }\r\n.Srskiltyttranderubrik { margin-top:0pt; margin-bottom:3.1pt; text-align:left; page-break-inside:avoid; page-break-after:avoid; line-height:12.5pt; font-family:'Verdana'; font-size:10.5pt; font-weight:bold }\r\n.TOC1 { margin-top:0pt; margin-right:28.35pt; margin-bottom:0pt; text-align:left; line-height:normal; font-family:'Verdana'; font-size:9.5pt }\r\n.TOC2 { margin:0pt 28.35pt 0pt 5.65pt; text-align:left; line-height:normal; font-family:'Verdana'; font-size:9.5pt }\r\n.TOC3 { margin:0pt 28.35pt 0pt 11.35pt; text-align:left; line-height:normal; font-family:'Verdana'; font-size:9.5pt }\r\n.TOC4 { margin:0pt 28.35pt 0pt 17pt; text-align:left; line-height:normal; font-family:'Verdana'; font-size:9.5pt }\r\n.TOC5 { margin:0pt 28.35pt 0pt 22.7pt; text-align:left; line-height:normal; font-family:'Verdana'; font-size:9.5pt }\r\n.TOC6 { margin-top:0pt; margin-left:47.65pt; margin-bottom:0pt; text-align:left; line-height:normal; font-family:'Verdana'; font-size:9.5pt }\r\n.TOC7 { margin-top:0pt; margin-right:28.35pt; margin-bottom:0pt; text-align:left; line-height:normal; font-family:'Verdana'; font-size:9.5pt }\r\n.TOC8 { margin-top:0pt; margin-right:28.35pt; margin-bottom:0pt; text-align:left; line-height:normal; font-family:'Verdana'; font-size:9.5pt }\r\n.TOC9 { margin-top:0pt; margin-left:8.5pt; margin-bottom:0pt; text-align:left; line-height:normal; font-family:'Verdana'; font-size:9.5pt }\r\n.TOCHeading { margin-top:3.1pt; margin-bottom:9pt; text-align:left; page-break-before:always; page-break-inside:avoid; page-break-after:avoid; line-height:12.5pt; font-family:'Verdana'; font-size:16pt }\r\n.Tabell-Kolumnrubrik { margin-top:3pt; margin-bottom:0pt; line-height:10pt; font-family:'Verdana'; font-size:8pt; font-weight:bold }\r\n.Tabell-KolumnrubrikHger { margin-top:3pt; margin-bottom:0pt; text-align:right; line-height:10pt; font-family:'Verdana'; font-size:8pt; font-weight:bold }\r\n.Tabell-Klla { margin-top:2pt; margin-bottom:0pt; line-height:8pt; font-family:'Verdana'; font-size:7pt }\r\n.Tabell-Radrubrik { margin-top:3pt; margin-bottom:0pt; line-height:10pt; font-family:'Verdana'; font-size:8pt }\r\n.Tabell-Rubrik { margin-top:12pt; margin-bottom:3pt; text-align:left; page-break-inside:avoid; page-break-after:avoid; line-height:10pt; font-family:'Verdana'; font-size:9pt; font-weight:bold }\r\n.Tabell-Siffror { margin-top:3pt; margin-bottom:0pt; text-align:right; line-height:10pt; font-family:'Verdana'; font-size:8pt }\r\n.Tabell-Text { margin-top:3pt; margin-bottom:0pt; line-height:10pt; font-family:'Verdana'; font-size:8pt }\r\n.Tabell-Underrubrik { margin-top:0pt; margin-bottom:1pt; text-align:left; page-break-inside:avoid; page-break-after:avoid; line-height:8pt; font-family:'Verdana'; font-size:8pt; font-weight:normal; font-style:italic }\r\n.TableofFigures { margin-top:3.1pt; margin-bottom:0pt; text-align:justify; line-height:normal; font-family:'Verdana'; font-size:9.5pt }\r\n.TillX-utskottet { margin-top:0pt; margin-bottom:12pt; text-align:left; page-break-after:avoid; line-height:12.5pt; font-family:'Verdana'; font-size:16pt }\r\n.Title { margin-top:3.1pt; margin-bottom:1pt; text-align:left; line-height:12pt; font-family:'Verdana'; font-size:20pt; letter-spacing:-0.5pt }\r\n.Vapen { margin-top:0pt; margin-bottom:0pt; text-align:left; page-break-inside:avoid; page-break-after:avoid; line-height:12.5pt; font-family:'Verdana'; font-size:16pt }\r\n.Yrkandelista { margin-top:3.1pt; margin-left:28.35pt; margin-bottom:0pt; text-indent:-28.35pt; text-align:justify; line-height:12.5pt; font-family:'Verdana'; font-size:9.5pt }\r\n.YrkandelistaEtt { margin-top:3.1pt; margin-left:0pt; margin-bottom:0pt; text-indent:0pt; text-align:justify; line-height:12.5pt; font-family:'Verdana'; font-size:9.5pt }\r\nspan.BallongtextChar { font-family:Tahoma; font-size:8pt }\r\nspan.BilagaChar { font-family:'Verdana'; font-size:8pt; font-variant:small-caps; text-decoration:underline }\r\nspan.BrdtextChar { font-family:'Verdana'; font-size:9.5pt }\r\nspan.BrdtextChar1 { font-family:'Verdana'; font-size:9.5pt }\r\nspan.Brdtextmedindrag2Char { font-family:'Verdana'; font-size:9.5pt }\r\nspan.CitatChar { font-family:'Verdana'; font-size:9.5pt }\r\nspan.DokumentRubrikChar { font-family:'Verdana'; font-size:18pt }\r\nspan.FotnotstextChar { font-family:'Verdana'; font-size:8pt }\r\nspan.FotnotstextindragChar { font-family:'Verdana'; font-size:8pt }\r\nspan.FrslagspunktChar { font-family:'Verdana'; font-size:9.5pt; font-weight:bold; font-style:normal }\r\nspan.Hyperlink { text-decoration:none; color:#000000; -aw-style-name:hyperlink }\r\nspan.KommentarerChar { font-family:'Verdana'; font-size:10pt }\r\nspan.NormalkursivChar { font-family:'Verdana'; font-size:9.5pt; font-style:italic }\r\nspan.NormaltindragChar { font-family:'Verdana'; font-size:9.5pt }\r\nspan.OrdfrandenChar { font-family:'Verdana'; font-size:9.5pt; font-style:italic }\r\nspan.OrtochDatumChar { font-family:'Verdana'; font-size:9.5pt }\r\nspan.PlaceholderText { color:#808080 }\r\nspan.PVgnarChar { font-family:'Verdana'; font-size:9.5pt }\r\nspan.ReservationshnvisningChar { font-family:'Verdana'; font-size:9.5pt; font-style:italic }\r\nspan.Rubrik1Char { font-family:'Verdana'; font-size:16pt }\r\nspan.Rubrik1DokumentinformationChar { font-family:'Verdana'; font-size:16pt }\r\nspan.Rubrik2Char { font-family:'Verdana'; font-size:13.5pt }\r\nspan.Rubrik3Char { font-family:'Verdana'; font-size:10.5pt; font-weight:bold }\r\nspan.Rubrik4Char { font-family:'Verdana'; font-size:10.5pt; font-style:italic; color:#000000 }\r\nspan.Rubrik5Char { font-family:'Verdana'; font-size:9.5pt; font-weight:bold }\r\nspan.Rubrik6Char { font-family:'Verdana'; font-size:9.5pt; font-style:italic; color:#000000 }\r\nspan.Rubrik7Char { font-family:'Verdana'; font-size:9.5pt; font-style:italic; color:#243f60 }\r\nspan.Rubrik8Char { font-family:'Verdana'; font-size:9pt; color:#272727 }\r\nspan.Rubrik9Char { font-family:'Verdana'; font-size:9pt; font-style:italic; color:#272727 }\r\nspan.RubrikChar { font-family:'Verdana'; font-size:20pt; letter-spacing:-0.5pt }\r\nspan.SidfotChar { font-family:'Verdana'; font-size:9.5pt }\r\nspan.SidhuvudChar { font-family:'Verdana'; font-size:7.5pt; font-variant:small-caps }\r\nspan.Tabell-Upphjttecken { font-family:'Verdana'; font-variant:normal; text-decoration:none; text-transform:none; vertical-align:super; display:inline }\r\nspan.VapenChar { font-family:'Verdana'; font-size:16pt }\r\nspan.tBilagaJA { color:#000000 }\r\nspan.tSidrubrikJA { color:#000000 }\r\n.PlainTable1 {  }\r\n.TableGrid {  }\r\n--></style>\r\n\r\n\t\t<div class=\"Section1\">\r\n\t\t\t<table cellspacing=\"0\" cellpadding=\"0\" style=\"margin-top:0pt; border-collapse:collapse\">\r\n\t\t\t\t<tr style=\"height:79.4pt; -aw-height-rule:exactly\">\r\n\t\t\t\t\t<td style=\"width:297.7pt; vertical-align:top\">\r\n\t\t\t\t\t\t<p class=\"Rubrik1Dokumentinformation\" style=\"line-height:16pt\">\r\n\t\t\t\t\t\t\t<span style=\"-aw-sdt-tag:'ccUtskott'; -aw-sdt-title:'utskottsnamn Dokumentegenskap'\"><span>Näringsutskottet</span></span><span style=\"-aw-sdt-tag:'ccS'; -aw-sdt-title:'s'\"><span>s</span></span><span style=\"-aw-sdt-tag:'ccMellanslag'; -aw-sdt-title:'Mellanslag'\"><span style=\"-aw-import:spaces\"> </span></span><a name=\"Utlatande\"></a><span>utlåtande</span>\r\n\t\t\t\t\t\t</p>\r\n\t\t\t\t\t\t<p class=\"Dokumentbeteckning\" style=\"line-height:16pt\">\r\n\t\t\t\t\t\t\t<span style=\"-aw-sdt-tag:'ccRiksmote'; -aw-sdt-title:'riksmote Dokumentegenskap'\"><span>2023/24</span></span><span style=\"-aw-sdt-tag:'ccKolon'; -aw-sdt-title:'Kolon'\"><span>:</span></span><a name=\"Utskottebeteckning\"></a><span>NU20</span>\r\n\t\t\t\t\t\t</p>\r\n\t\t\t\t\t\t<p class=\"Rubrik1Dokumentinformation\" style=\"line-height:16pt\">\r\n\t\t\t\t\t\t\t<span style=\"-aw-import:ignore\"> </span>\r\n\t\t\t\t\t\t</p>\r\n\t\t\t\t\t</td>\r\n\t\t\t\t</tr>\r\n\t\t\t</table>\r\n\t\t\t<div style=\"-aw-sdt-tag:'ccDokumentrubrik'; -aw-sdt-title:'dokumentrubrik Dokumentegenskap'\">\r\n\t\t\t\t<p class=\"DokumentRubrik\">\r\n\t\t\t\t\t<span>Kommissionens vitbok om utgående investeringar</span>\r\n\t\t\t\t</p>\r\n\t\t\t</div>\r\n\t\t\t<p class=\"Sammanfattning\" style=\"line-height:16pt\">\r\n\t\t\t\t<span class=\"tSidrubrikJA\">Sammanfattning</span>\r\n\t\t\t</p>\r\n\t\t\t<p>\r\n\t\t\t\t<span>Utskottet har granskat kommissionens vitbok om utgående investeringar och föreslår att riksdagen lägger utlåtandet till handlingarna.</span>\r\n\t\t\t</p>\r\n\t\t\t<p class=\"NormalIndent\">\r\n\t\t\t\t<span>Utskottet instämmer i att det kan finnas skäl att se över potentiella risker för teknik- och kunskapsläckage som kan uppstå till följd av utgående investeringar som kommissionen lyfter i vitboken. Ett övervakningssystem som kommissionen för fram skulle kunna vara ett av flera tillvägagångssätt att få information om känsliga teknikområdena. Samtidigt bör de åtgärder som eventuellt vidtas vara proportionerliga och sträva efter en balans mellan att säkerställa att känsliga teknologier eller kunskap inte faller i orätta händer och att upprätthålla en global marknad som är konkurrenskraftig för den framtida utvecklingen av den svenska och europeiska ekonomin. Utskottet anser att de idéer som förs fram i vitboken noggrant behöver granskas och utvärderas när det gäller risker och möjligheter, särskilt i relation till strategiskt skyddsvärd teknologi och kunskap, innan några nya åtgärder kan vidtas. </span>\r\n\t\t\t</p>\r\n\t\t\t<p class=\"NormalIndent\">\r\n\t\t\t\t<span>Utlåtandet innehåller en motivreservation (V, MP). </span>\r\n\t\t\t</p>\r\n\t\t\t<p class=\"R4\">\r\n\t\t\t\t<span>Granskade dokument</span>\r\n\t\t\t</p>\r\n\t\t\t<p>\r\n\t\t\t\t<span>Kommissionens vitbok om utgående investeringar, COM(2024) 24.</span>\r\n\t\t\t</p>\r\n\t\t\t<p>\r\n\t\t\t\t<span style=\"-aw-import:ignore\"> </span>\r\n\t\t\t</p>\r\n\t\t\t<p>\r\n\t\t\t\t<span style=\"-aw-import:ignore\"> </span>\r\n\t\t\t</p>\r\n\t\t\t<p class=\"Innehllsfrteckning\">\r\n\t\t\t\t<a name=\"Innehållsförteckning\"></a><span class=\"tSidrubrikJA\">Innehållsförteckning</span>\r\n\t\t\t</p>\r\n\t\t\t<p class=\"TOC1\">\r\n\t\t\t\t<a href=\"#_Toc166749278\" style=\"text-decoration:none\"><span class=\"Hyperlink\">Utskottets förslag till riksdagsbeslut</span></a>\r\n\t\t\t</p>\r\n\t\t\t<p class=\"TOC1\">\r\n\t\t\t\t<a href=\"#_Toc166749279\" style=\"text-decoration:none\"><span class=\"Hyperlink\">Redogörelse för ärendet</span></a>\r\n\t\t\t</p>\r\n\t\t\t<p class=\"TOC1\">\r\n\t\t\t\t<a href=\"#_Toc166749280\" style=\"text-decoration:none\"><span class=\"Hyperlink\">Utskottets överväganden</span></a>\r\n\t\t\t</p>\r\n\t\t\t<p class=\"TOC2\">\r\n\t\t\t\t<a href=\"#_Toc166749281\" style=\"text-decoration:none\"><span class=\"Hyperlink\">Kommissionens vitbok om utgående investeringar</span></a>\r\n\t\t\t</p>\r\n\t\t\t<p class=\"TOC3\">\r\n\t\t\t\t<a href=\"#_Toc166749282\" style=\"text-decoration:none\"><span class=\"Hyperlink\">Utskottets ställningstagande</span></a>\r\n\t\t\t</p>\r\n\t\t\t<p class=\"TOC1\">\r\n\t\t\t\t<a href=\"#_Toc166749283\" style=\"text-decoration:none\"><span class=\"Hyperlink\">Reservation</span></a>\r\n\t\t\t</p>\r\n\t\t\t<p class=\"TOC6\" style=\"margin-right:17pt; margin-left:5.65pt\">\r\n\t\t\t\t<a href=\"#_Toc166749284\" style=\"text-decoration:none\"><span class=\"Hyperlink\">Kommissionens vitbok om utgående investeringar – motiveringen (V, MP)</span></a>\r\n\t\t\t</p>\r\n\t\t\t<p class=\"TOC8\">\r\n\t\t\t\t<span class=\"Hyperlink\" style=\"font-style:italic\">Bilaga</span><br><a href=\"#_Toc166749285\" style=\"text-decoration:none\"><span class=\"Hyperlink\">Förteckning över granskade dokument</span></a>\r\n\t\t\t</p>\r\n\t\t\t<p class=\"Fluglort\">\r\n\t\t\t</p>\r\n\t\t\t<p class=\"Fluglort\">\r\n\t\t\t\t<span style=\"-aw-import:ignore\"> </span>\r\n\t\t\t</p>\r\n\t\t\t<p class=\"Avsnittsrubrik\">\r\n\t\t\t\t<a name=\"StopCC\"></a><a name=\"_Toc166749278\"><span style=\"-aw-bookmark-end:StopCC\"></span><span class=\"tSidrubrikJA\">Utskottets förslag till riksdagsbeslut</span></a>\r\n\t\t\t</p>\r\n\t\t\t<div style=\"-aw-sdt-tag:'dokumentavsnitt/utskottets förslag till riksdagsbeslut/-1024463253/1715849619654'; -aw-sdt-title:'utskottets förslag till riksdagsbeslut'\">\r\n\t\t\t\t<p class=\"Mellanrum\">\r\n\t\t\t\t\t<span style=\"-aw-import:spaces\"> </span>\r\n\t\t\t\t</p>\r\n\t\t\t\t<p class=\"Mellanrum\">\r\n\t\t\t\t\t<span style=\"-aw-import:spaces\"> </span>\r\n\t\t\t\t</p>\r\n\t\t\t\t<table cellspacing=\"0\" cellpadding=\"0\" style=\"width:294.2pt; margin-top:0pt; border-collapse:collapse\">\r\n\t\t\t\t\t<tr style=\"page-break-inside:avoid\">\r\n\t\t\t\t\t\t<td style=\"width:22pt; vertical-align:top\">\r\n\t\t\t\t\t\t\t<p style=\"text-align:justify; page-break-inside:avoid; page-break-after:avoid; line-height:12.5pt\">\r\n\t\t\t\t\t\t\t\t<span style=\"font-size:10.5pt; font-weight:bold\">Kommissionens vitbok om utgående investeringar</span>\r\n\t\t\t\t\t\t\t</p>\r\n\t\t\t\t\t\t</td>\r\n\t\t\t\t\t</tr>\r\n\t\t\t\t</table>\r\n\t\t\t\t<p class=\"Normalutanluftfre\">\r\n\t\t\t\t\t<span>Riksdagen lägger utlåtandet till handlingarna.</span><span> </span>\r\n\t\t\t\t</p>\r\n\t\t\t\t<p class=\"Reservationshnvisning\">\r\n\t\t\t\t\t<span>Reservation (V, MP) – motiveringen</span>\r\n\t\t\t\t</p>\r\n\t\t\t\t<p class=\"OrtochDatum\">\r\n\t\t\t\t\t<span>Stockholm den 16 maj 2024</span>\r\n\t\t\t\t</p>\r\n\t\t\t\t<p class=\"PVgnar\">\r\n\t\t\t\t\t<span>På näringsutskottets vägnar</span>\r\n\t\t\t\t</p>\r\n\t\t\t\t<p class=\"Ordfranden\">\r\n\t\t\t\t\t<span>Tobias Andersson</span>\r\n\t\t\t\t</p>\r\n\t\t\t\t<p class=\"Deltagare\">\r\n\t\t\t\t\t<span>Följande ledamöter har deltagit i beslutet: Tobias Andersson (SD), Elisabeth Thand Ringqvist (C), Fredrik Olovsson (S), Mats Green (M), Monica Haider (S), Mattias Jonsson (S), Ann-Charlotte Hammar Johnsson (M), Isak From (S), Kjell Jansson (M), Eric Palmqvist (SD), Louise Eklund (L), Johnny Svedin (SD), Aida Birinxhiku (S), Lorena Delgado Varas (V), Lili André (KD), Linus Lakso (MP) och Anette Rangdag (SD).</span>\r\n\t\t\t\t</p>\r\n\t\t\t\t<p class=\"Mellanrum\">\r\n\t\t\t\t\t<span style=\"-aw-import:ignore\"> </span>\r\n\t\t\t\t</p>\r\n\t\t\t\t<p class=\"Mellanrum\">\r\n\t\t\t\t\t<span style=\"-aw-import:ignore\"> </span>\r\n\t\t\t\t</p>\r\n\t\t\t\t<p class=\"Mellanrum\">\r\n\t\t\t\t\t<span style=\"font-size:9.5pt; -aw-import:ignore\"> </span>\r\n\t\t\t\t</p>\r\n\t\t\t</div>\r\n\t\t\t<p class=\"Avsnittsrubrik\">\r\n\t\t\t\t<a name=\"SlutUtskottsForslag\"></a><a name=\"_Toc166749279\"><span style=\"-aw-bookmark-end:SlutUtskottsForslag\"></span><span class=\"tSidrubrikJA\">Redogörelse för ärendet</span></a>\r\n\t\t\t</p>\r\n\t\t\t<p class=\"NormalIndent\" style=\"text-indent:0pt\">\r\n\t\t\t\t<span>Kommissionen presenterade den 24 januari 2024 en vitbok om utgående investeringar i samband med ett paket från kommissionen om att stärka EU:s ekonomiska säkerhet, COM(2024) 24. </span>\r\n\t\t\t</p>\r\n\t\t\t<p class=\"NormalIndent\">\r\n\t\t\t\t<span>Talmannen beslutade den 13 mars 2024 efter samråd med gruppledarna i enlighet med 9 kap. 20 § riksdagsordningen att hänvisa kommissionens vitbok till näringsutskottet för granskning och dokumentet hänvisades till utskottet den 14 mars 2024. </span>\r\n\t\t\t</p>\r\n\t\t\t<p class=\"NormalIndent\">\r\n\t\t\t\t<span>Utskotten ska enligt 10 kap. 3 § andra stycket riksdagsordningen lämna ut</span><span>­</span><span>låtanden till kammaren över de EU-dokument som har hänvisats till dem. Efter beslutet i kammaren skickar Riksdagsförvaltningen utlåtandet för kännedom till kommissionen och till Regeringskansliet.</span>\r\n\t\t\t</p>\r\n\t\t\t<p class=\"NormalIndent\">\r\n\t\t\t\t<span>Den 27 februari 2024 överlämnade Regeringskansliet faktapromemoria 2023/24:FPM41 med anledning av kommissionens vitbok om utgående investeringar, och den 2 maj 2024 överlade utskottet med regeringen om regeringen ståndpunkt om vitboken (prot. 2023/24:29).</span>\r\n\t\t\t</p>\r\n\t\t\t<p class=\"NormalIndent\" style=\"text-indent:0pt\">\r\n\t\t\t\t<span style=\"-aw-import:ignore\"> </span>\r\n\t\t\t</p>\r\n\t\t\t<p class=\"NormalIndent\">\r\n\t\t\t\t<span style=\"-aw-import:ignore\"> </span>\r\n\t\t\t</p>\r\n\t\t\t<p class=\"Avsnittsrubrik\">\r\n\t\t\t\t<a name=\"_Toc166749280\"><span class=\"tSidrubrikJA\">Utskottets överväganden</span></a>\r\n\t\t\t</p>\r\n\t\t\t<div style=\"-aw-sdt-tag:'8bf01863-e1ee-441a-bb22-2c08276e2bda/förslagsrutor/1999634128/1715083142579'; -aw-sdt-title:'förslagsrutor'\">\r\n\t\t\t\t<h2 style=\"line-height:13.5pt\">\r\n\t\t\t\t\t<a name=\"_Toc166749281\"><span>Kommissionens vitbok om utgående investeringar</span></a>\r\n\t\t\t\t</h2>\r\n\t\t\t</div>\r\n\t\t\t<span style=\"-aw-bookmark-end:_Toc166749281\">\r\n\t\t\t</span>\r\n\t\t\t<div style=\"margin-top:3.1pt; margin-right:0.9pt; margin-left:0.9pt; border:0.75pt solid #000000; -aw-border:0.5pt single; clear:both\">\r\n\t\t\t\t<p class=\"Normalrutafet\" style=\"margin-top:0pt; margin-right:0pt; margin-left:0pt; border-style:none; padding-bottom:0pt\">\r\n\t\t\t\t\t<span>Utskottets förslag i korthet</span>\r\n\t\t\t\t</p>\r\n\t\t\t\t<p class=\"Normalruta\" style=\"margin-top:0pt; margin-right:0pt; margin-left:0pt; border-style:none; padding-top:0pt; padding-bottom:0pt\">\r\n\t\t\t\t\t<span>Riksdagen lägger utlåtandet till handlingarna.</span>\r\n\t\t\t\t</p>\r\n\t\t\t\t<div style=\"-aw-sdt-tag:'8bf01863-e1ee-441a-bb22-2c08276e2bda/förslagsrutor reservations text/-1038224701/1715612665609'; -aw-sdt-title:'förslagsrutor reservations text'\">\r\n\t\t\t\t\t<p class=\"Normalrutaindrag\" style=\"margin-right:0pt; margin-left:0pt; border-style:none; padding-top:0pt\">\r\n\t\t\t\t\t\t<span>Jämför motivreservationen (V, MP).</span>\r\n\t\t\t\t\t</p>\r\n\t\t\t\t</div>\r\n\t\t\t</div>\r\n\t\t\t<p class=\"R3\">\r\n\t\t\t\t<span>Bakgrund</span>\r\n\t\t\t</p>\r\n\t\t\t<p>\r\n\t\t\t\t<span>Den 20 juni 2023 informerade kommissionen om lanseringen av en europeisk strategi för att stärka den ekonomiska säkerheten (COM(2023) 20 final, faktapromemoria 2022/23:FPM115), vilket inkluderade ett förslag på att skapa en expertgrupp som är dedikerad till att analysera utgående investeringar. Denna grupp är avsedd att överväga EU:s strategiska tillvägagångssätt för att hantera ekonomisk säkerhet i ljuset av globala geopolitiska förändringar, samt att identifiera risker som dessa investeringar kan medföra. </span>\r\n\t\t\t</p>\r\n\t\t\t<p class=\"NormalIndent\">\r\n\t\t\t\t<span>Vitboken introduceras som en del av ett omfattande paket om ekonomisk säkerhet (COM(2024) 22 final), som inkluderar ett förslag till lag om översyn av utländska direktinvesteringar (COM(2024) 23), en vitbok om kontroll av export (COM(2024) 25), en rekommendation för säkerhetsåtgärder inom forskning utfärdad av rådet (COM(2024) 26), och en vitbok om forskning inom teknologi som kan ha dubbla användningsområden (COM(2024) 27). </span>\r\n\t\t\t</p>\r\n\t\t\t<p class=\"NormalIndent\">\r\n\t\t\t\t<span>Dessa åtgärder utgör en del av kommissionens och EU-medlemsstaternas gemensamma ansträngningar för att förbättra den ekonomiska säkerheten. Vitbokens innehåll och rekomm</span><span>­</span><span>endationer är direkt influerade av de överlägg</span><span>­</span><span>ningar som har förts inom den specifika expertgruppen.</span>\r\n\t\t\t</p>\r\n\t\t\t<p class=\"R3\">\r\n\t\t\t\t<a name=\"_Hlk164874483\"><span>Kommissionens vitbok</span></a>\r\n\t\t\t</p>\r\n\t\t\t<p>\r\n\t\t\t\t<span>Kommissionens vitbok om utgående investeringar beskriver och rekommen</span><span>­</span><span>derar olika tillvägagångssätt och strategier för att hantera potentiella säkerhets</span><span>­</span><span>risker som är förknippade med investeringar utanför EU, särskilt när det gäller känslig teknologi. </span>\r\n\t\t\t</p>\r\n\t\t\t<p class=\"NormalIndent\">\r\n\t\t\t\t<a name=\"_Hlk166491483\"><span>Vitboken framhåller EU:s ekonomiska framgång och säkerhet som beroende av öppna globala marknader, samtidigt som den pekar på potentiella säkerhetsrisker som kan uppstå från känslig teknik och investeringar som lämnar EU. Specifikt identifieras en växande oro för att utgående invester</span><span>­</span><span>ingar, särskilt när det gäller avancerad teknik, kan hamna i fel händer och därmed äventyra EU:s säkerhet. </span></a>\r\n\t\t\t</p>\r\n\t\t\t<p class=\"NormalIndent\">\r\n\t\t\t\t<span style=\"-aw-bookmark-end:_Hlk166491483\"></span><span>Syftet med vitboken är att utforma en effektiv EU-strategi för att förstå och hantera riskerna med utgående investeringar. Målet är att säkerställa att EU och dess medlemsstater kan skydda sin ekonomiska säkerhet utan att kompromissa med den inre marknadens öppenhet och konkurrenskraft.</span>\r\n\t\t\t</p>\r\n\t\t\t<p class=\"NormalIndent\">\r\n\t\t\t\t<span>Vitboken belyser de komplexa och känsliga dimensionerna av utgående investeringar och rekommenderar en gradvis strategi för att ta itu med dessa utmaningar, i nära samarbete med medlemsstaterna, genom en expertgrupp. De diskussioner som har ägt rum inom expertgruppen för utgående invester</span><span>­</span><span>ingar har belyst en brist på information som behövs för att effektivt identifiera och bedöma eventuella risker som är förknippade med utgående investeringar. Kommissionen uppmanar därför medlemsstaterna att samla in och dela relevant information för riskbedömning samt att systematiskt utvärdera utgående investeringar ur ett säkerhetsperspektiv. Kommissionen rekommen</span><span>­</span><span>derar medlemsstaterna att under ett års tid övervaka utgående investeringar och samla in information retroaktivt från perioden 2019–2024.</span>\r\n\t\t\t</p>\r\n\t\t\t<p class=\"NormalIndent\">\r\n\t\t\t\t<span>För att hantera dessa identifierade risker rekommenderar kommissionen en utformad övervakningsprocess för medlemsstaterna. Vitboken fokuserar på övervakning och riskbedömning av utgående investeringar inom fyra teknikområden: avancerade halvledare, artificiell intelligens, kvantteknik, och bioteknik. Dessa områden har i vitboken identifierats som kritiska för EU:s ekonomiska säkerhet, och kommissionen rekommenderar att medlemsstaterna lägger fokus på dessa fyra valda teknikområden.</span>\r\n\t\t\t</p>\r\n\t\t\t<p class=\"NormalIndent\">\r\n\t\t\t\t<span>Det föreslagna övervakningssystemet omfattar ett brett spektrum av trans</span><span>­</span><span>aktioner och syftar till att samla in detaljerad information om dessa inves</span><span>­</span><span>teringar för att möjli</span><span>­</span><span>ggöra en effektiv risk</span><span>­</span><span>bedömning. Dessutom rekomm</span><span>­</span><span>enderas en parallell översyn av exportlicenser för produkter med dubbla användningsområden som är kopplade till utgående investeringar, för att ytterligare minska riskerna för utflöde av känslig teknik och bidra till säkerhet.</span><span> </span>\r\n\t\t\t</p>\r\n\t\t\t<p class=\"NormalIndent\">\r\n\t\t\t\t<span>En viktig del av vitbokens strategi handlar om att fastställa tillämpnings</span><span>­</span><span>området för övervakningen. Tillämpningsområdet för övervak</span><span>­</span><span>ningen är, enligt rekom</span><span>­</span><span>men</span><span>­</span><span>dationen i vitboken, inriktat på att täcka ett brett spektrum av trans</span><span>­</span><span>aktioner och verksamheter som är relaterade till utgående investeringar från EU till tredjeländer. Det gäller bl.a. förvärv av företag, sammanslagningar av bolag, överföring av tillgångar, uppstart av företag och samriskföretag. Vitboken specificerar att övervakningen bör inkludera alla typer av aktiva investeringar som har gjorts av fysiska eller juridiska personer som är bosatta eller etablerade inom EU, med syftet att bedriva ekonomisk verksamhet utanför unionen. Tillämpningsområdet sträcker sig även till att inkludera indirekta investeringar som görs genom enheter i tredjeländer som används som investeringsverktyg, genom befintliga dotterbolag, eller inom ramen för befintliga samriskföretag. Detta kan inbegripa gradvisa överföringar av tillgångar över tid, investeringar i tredjeländer som en följd av tidigare investeringar, samt investeringar som syftar till att kringgå befintliga säker</span><span>­</span><span>hetsrelaterade handels- och investeringskontroller. </span>\r\n\t\t\t</p>\r\n\t\t\t<p class=\"NormalIndent\">\r\n\t\t\t\t<span style=\"-aw-import:ignore\"> </span>\r\n\t\t\t</p>\r\n\t\t\t<p class=\"NormalIndent\">\r\n\t\t\t\t<span>Medlemsstaterna uppmuntras även att överväga frivillig övervakning av andra kritiska aktiviteter som är relaterade till utgående investeringar, såsom forsknings- och utvecklingssamarbeten, och metoder för att attrahera hög</span><span>­</span><span>kvalificerad personal, vilket också kan leda till risker för utflöde av känslig teknik eller kunskap. Vidare förväntas medlemsstaterna använda befintliga instrument för att hantera de risker som identifieras och, där det behövs, utveckla nya verktyg och processer.</span>\r\n\t\t\t</p>\r\n\t\t\t<p class=\"NormalIndent\">\r\n\t\t\t\t<span>För att effektivisera genomförandet av det som förs fram i vitboken, rekommenderar kommissionen att varje medlemsstat anförtror en särskild myndighet ansvaret för denna övervakning, där befintliga verktyg och meka</span><span>­</span><span>nismer ska användas för att upptäcka risker. Vitboken under</span><span>­</span><span>­</span><span>stryker även vikten av att involvera ett brett spek</span><span>­</span><span>trum av berörda parter, inkl</span><span>­</span><span>usive närings</span><span>­</span><span>livet, den akademiska världen och det civila samhället, i övervaknings</span><span>­</span><span>processen. En objektiv syn på tredjeländer rekomm</span><span>­</span><span>enderas som grund för övervakningen, men medlemsstaterna uppmanas att fokusera på specifika destinationer enligt riskbedömningar av vissa länder. </span>\r\n\t\t\t</p>\r\n\t\t\t<p class=\"NormalIndent\">\r\n\t\t\t\t<span>Vitboken betonar vikten av fortsatt arbete för att utveckla en effektiv och enhetlig EU-strategi. Kommissionen anger även behovet av att prioritera användningen av befintliga instrument innan nya initiativ eller politiska åtgärder övervägs.</span>\r\n\t\t\t</p>\r\n\t\t\t<p class=\"R3\">\r\n\t\t\t\t<span>Regeringens faktapromemoria</span>\r\n\t\t\t</p>\r\n\t\t\t<p class=\"NormalIndent\" style=\"text-indent:0pt\">\r\n\t\t\t\t<a name=\"_Hlk163658904\"><span>Regeringskansliet överlämnade med anledning av kommissionens vitbok om utgående investeringar faktapromemoria 2023/24:FPM41 till riksdagen. Av regeringens preliminära ståndpunkt som redovisas i promemorian framgår följande:</span></a>\r\n\t\t\t</p>\r\n\t\t\t<p class=\"Quote\">\r\n\t\t\t\t<span>Regeringen anser att det är viktigt att förstå och analysera risker samt möjligheter med utgående investeringar, innan ställning kan tas till ett eventuellt behov av att vidta nya åtgärder. Det är särskilt viktigt att förstå och analysera risker och möjligheter med strategiskt skyddsvärd teknologi och kunskap. Det av kommissionen rekommenderade tillvägagångssättet med införandet av en övervakning av utgående investeringar skulle kunna vara ett av flera sätt att få information. Behovet och lämpligheten av övervakning av utgående investeringar måste analyseras och övervägas med försiktighet. En avvägning behövs huruvida en övervakning av utgående investeringar är proportionerlig och om kostnaderna och den administrativa bördan för medlemsstaterna och företagen kan motiveras i förhållande till syftet. Medlemsstaternas fördragsfästa ansvar för nationell säkerhet måste säkerställas i förhållande till den information som förutses delas med kommissionen.</span>\r\n\t\t\t</p>\r\n\t\t\t<p class=\"R3\" style=\"margin-bottom:0pt\">\r\n\t\t\t\t<span style=\"-aw-bookmark-end:_Hlk164874483\"></span><span style=\"-aw-bookmark-end:_Hlk163658904\"></span><span>Bakgrund och pågående arbete</span>\r\n\t\t\t</p>\r\n\t\t\t<p class=\"R4\" style=\"margin-top:6pt\">\r\n\t\t\t\t<span>Inledning</span>\r\n\t\t\t</p>\r\n\t\t\t<p>\r\n\t\t\t\t<span>Utskottet beslutade den 14 mars 2024 att överlägga med regeringen om den svenska ståndpunkten om vitboken (prot. 2023/24:21). Utskottet överlade med regeringen den 2 maj 2024, och då uttryckte utskottet stöd för regeringens ståndpunkt (prot. 2023/24:29). </span>\r\n\t\t\t</p>\r\n\t\t\t<p class=\"NormalIndent\">\r\n\t\t\t\t<span>Den 19 oktober 2023 överlade utskottet med regeringen om lanseringen av en europeisk strategi för att stärka den ekonomiska säkerheten (COM(2023) 20 final, 2022/23:FPM115), vilket inkluderade ett förslag på att skapa en expertgrupp som är dedikerad till att analysera utgående investeringar. Utskottet uttryckte då stöd för regeringens ståndpunkt (prot. 2023/24:6).</span>\r\n\t\t\t</p>\r\n\t\t\t<p class=\"R4\">\r\n\t\t\t\t<span>Kommerskollegiums utredning</span>\r\n\t\t\t</p>\r\n\t\t\t<p>\r\n\t\t\t\t<span>I utredningen Analys om granskning av utgående investeringar, som har utarbetats av Kommerskollegium, granskas konsekvenserna av potentiella regelverk som rör utgående investeringar i Sverige. Utredningen inleds med en övergripande analys av hur liknande system för granskning har genomförts internationellt och vilken påverkan dessa system har haft på de berörda ländernas ekonomier och företagssektorer. </span>\r\n\t\t\t</p>\r\n\t\t\t<p class=\"NormalIndent\">\r\n\t\t\t\t<span>Utredningen framhåller att utgående investeringar är centrala för svenska företags förmåga att växa och konkurrera globalt, särskilt när det gäller att etablera sig på nya marknader och öka den operationella effektiviteten. </span>\r\n\t\t\t</p>\r\n\t\t\t<p class=\"NormalIndent\">\r\n\t\t\t\t<span>Fokus läggs sedan på de specifika risker och utmaningar som ett strikt granskningssystem för utgående investeringar kan medföra. Utredningen belyser bekymmer om att ett omfattande och rigitt system kan försvåra för svenska företags möjligheter att agera fritt på internationella arenor, vilket potentiellt kan leda till negativa ekonomiska konsekvenser för Sverige. Dessa risker inkluderar en ökad administrativ börda och potentiella förseningar i genomförandet av gränsöverskridande affärstransaktioner. Utredningen disku</span><span>­</span><span>terar även risken att sådana system kan missbrukas för protektionistiska ändamål, vilket skulle kunna underminera den svenska öppna marknads</span><span>­</span><span>ekonomin.</span>\r\n\t\t\t</p>\r\n\t\t\t<p class=\"NormalIndent\">\r\n\t\t\t\t<span>Kommerskollegium förespråkar en noggrann utformning av gransknings</span><span>­</span><span>systemet, med tydliga kriterier och mål, för att minimera dess inverkan på företagens internationella verksamhet och den bredare ekonomiska dyna</span><span>­</span><span>miken. Myndigheten pekar på att det som förs fram i vitboken om ett övervak</span><span>­</span><span>ning</span><span>­</span><span>s</span><span>­</span><span>­</span><span>system</span><span>­</span><span> kräver omfattande datainsamling som inkluderar sekrete</span><span>­</span><span>ss</span><span>­</span><span>belagd information. För att förbättra ut</span><span>­</span><span>for</span><span>­</span><span>­</span><span>mningen rekom</span><span>­</span><span>m</span><span>­</span><span>­</span><span>enderar Kommers</span><span>­</span><span>kollegium att data</span><span>­</span><span>­</span><span>insamlingen preciseras och bör baseras på off</span><span>­</span><span>entligt till</span><span>­</span><span>gängliga uppgifter. Myndigheten föreslår även en min</span><span>­</span><span>i</span><span>­</span><span>mering av de admin</span><span>­</span><span>istrativa kraven och den regelbörda som är förknippad med den föreslagna data</span><span>­</span><span>insamlingen. Det efterlyses ett framtida grans</span><span>­</span><span>kning</span><span>­</span><span>ssystem som är transparent och förutsägbart för att undvika att negativt påverka företagens konkurrenskraft och lönsamhet. </span>\r\n\t\t\t</p>\r\n\t\t\t<p class=\"NormalIndent\">\r\n\t\t\t\t<span>Slutligen framhåller Kommerskollegium vikten av en detaljerad konse</span><span>­</span><span>kvens</span><span>­</span><span>­</span><span>analys från kommissionen som klarlägger den ökade regelbörda som datainsamlingen innebär, och ger en tydligare bild av de risker som förknippas med utgående investeringar i ljuset av den ekonomiska säkerhetsstrategin.</span>\r\n\t\t\t</p>\r\n\t\t\t<h3 style=\"margin-bottom:0pt\">\r\n\t\t\t\t<a name=\"_Toc166749282\"><span>Utskottets ställningstagande</span></a>\r\n\t\t\t</h3>\r\n\t\t\t<p>\r\n\t\t\t\t<a name=\"_Hlk165294540\"><span>Som redogjorts för inledningsvis i detta utlåtande innehåller kommissionens vitbok en inriktning för det fortsatta arbetet med utgående investeringar och de risker som dessa investeringar kan innebära till följd av att teknik eller kunskap hamnar i fel händer. Då det i dagsläget råder en informationsbrist om vilka utgående investeringar som görs från EU till länder utanför unionen presenterar kommissionen en stegvis ansats. Vit</span><span>­</span><span>boken fram</span><span>­</span><span>håller EU:s ekonomiska framgång och säkerhet som beroende av öppna globala marknader. Samtidigt pekar den på potentiella säkerhetsrisker som kan uppstå från känslig teknik och investeringar som lämnar EU. Syftet med vitboken är att utforma en effektiv EU-strategi för att förstå och hantera riskerna med utgående investeringar. För att hantera dessa identifierade risker rekommen</span><span>­</span><span>derar kommissionen en utformad övervakningsprocess för medlemsstaterna. Vitboken fokuserar på övervakning och riskbedömning av utgående investeringar inom fyra teknikområden: avancerade halvledare, artificiell intelligens, kvantteknik, och bioteknik. Dessa områden har i vitboken identi</span><span>­</span><span>fierats som kritiska för EU:s ekonomiska säkerhet, och kommissionen rekomm</span><span>­</span><span>enderar att medlem</span><span>­</span><span>sstaterna lägger fokus på dessa fyra utvalda teknikområden.</span></a>\r\n\t\t\t</p>\r\n\t\t\t<p class=\"NormalIndent\">\r\n\t\t\t\t<span>Utskottet vill med anledning av vitboken inledningsvis framhålla sin uppfattning att handel och investeringar är grundläggande förutsättningar för ekonomisk tillväxt och välstånd såväl i Sverige som övriga EU. Genom att upp</span><span>­</span><span>rätt</span><span>­</span><span>hålla och främja en fri handel, samt genom att öppna investerings</span><span>­</span><span>kanaler stärker Sverige och EU:s övriga medlemsländer konkurrenskraften, stimulerar innovation och underlättar tillgången till globala marknader. Dessa principer är avgörande för att säkra ekonomisk stabilitet och främja internationellt samarbete och ekonomisk integration. En dynamisk och en väl fungerande handelsmiljö bidrar inte bara till ekonomisk tillväxt i enskilda länder utan stöder också global ekonomisk sammanhållning och resiliens mot ekonomiska störningar. Därför är det angeläget att EU fortsätter att sträva efter en handels- och investeringspolitik som är fri från onödiga hinder och restriktioner, och som aktivt arbetar för att minska administrativa bördor och förenkla regler som gynnar alla involverade parter. </span>\r\n\t\t\t</p>\r\n\t\t\t<p class=\"NormalIndent\">\r\n\t\t\t\t<span>Samtidigt kan man inte blunda för de potentiella risker för teknik- och kunskapsläckage som kan uppstå till följd av utgående investeringar som kommissionen försöker adressera i vitboken. Som kommissionen påpekar i vitboken är EU inte först med att överväga politiska initiativ på detta område. Vissa länder kontrollerar redan utgående investeringar medan andra länder håller på att utveckla en ram för detta. Mot den bakgrunden välkomnar utskottet en diskussion utifrån vitboken. </span>\r\n\t\t\t</p>\r\n\t\t\t<p class=\"NormalIndent\">\r\n\t\t\t\t<span>Utskottet noterar att företrädare för svenska företag, bl.a. Svenskt Näringsliv i positionspapperet Building security through competitiveness, har uttryckt farhågor om de utmaningar som svenska företag och branschorganisationer eventuellt kan möta när det gäller de åtgärder som kommissionen för fram i vitboken. Bland de identifierade riskerna framhävs särskilt bekymren som rör det föreslagna systemet för granskning av dessa investeringar, vilket kan inverka negativt på svenska företags möjligheter att konkurrera på en global marknad. Det argumenteras bl.a. för att sådana åtgärder riskerar att skapa onödiga fördröjningar i kapitalflöden, vilket kan skada företagens expansionsplaner och även EU:s övergripande ekonomiska intressen samt bli ett potentiellt verktyg för protektionism. Därmed finns en risk att ett mer omfattande granskningssystem troligen skulle begränsa företagens förmåga att agera fritt internationellt, vilket kan ha skadliga effekter för svensk ekonomi och välfärd. Enligt utskottets uppfattning behöver ovan nämnda farhågor beaktas i det fortsatta arbetet. </span>\r\n\t\t\t</p>\r\n\t\t\t<p class=\"NormalIndent\">\r\n\t\t\t\t<span>Vidare har utskottet noterat den analys om granskning utgående investeringar som Kommerskollegium har gjort. Som redogjorts för i det före</span><span>­</span><span>gående framhåller Kommerskollegium i sin rapport att utgående investeringar är centrala för svenska företags förmåga att växa och konkurrera globalt, särskilt när det gäller att etablera sig på nya marknader och öka den operationella effektiviteten. Vidare redogörs det för de specifika risker och utmaningar som ett strikt granskningssystem för utgående investeringar kan medföra. Utredningen belyser bekymmer om att ett omfattande och rigitt system kan försvåra för svenska företags möjligheter att agera fritt på internationella arenor, vilket potentiellt kan leda till negativa ekonomiska konsekvenser för Sverige. Dessa risker inkluderar en ökad administrativ börda och potentiella förseningar i genomförandet av gränsöverskridande affärs</span><span>­</span><span>transaktioner. Utredningen diskuterar även risken att sådana system kan missbrukas för protektionistiska ändamål, vilket skulle kunna underminera den svenska öppna marknadsekonomin. Mot denna bakgrund förespråkar Kommerskollegium en noggrann utformning av granskningssystemet, med tydliga kriterier och mål, för att minimera dess inverkan på företagens internationella verksamhet och den bredare ekonomiska dynamiken. Utskottet har därtill noterat några av de rekommendationer som Kommerskollegium har gett uttryck för. Det handlar om behovet av att precisera och avgränsa komm</span><span>­</span><span>issionens idé, att data</span><span>­</span><span>insamling i första hand bör baseras på offentligt tillgängliga uppgifter och att omfattningen av och detaljnivån på infor</span><span>­</span><span>mationen som samlas in bör begränsas för att minimera administrativ börda för företag och myndigheter. Vidare har Kommerskollegium pekat på behovet av att det genomförs en konsekvensanalys som tar hänsyn till företagens ökade regelbörda tillsammans med en tydliggjord riskbild, att definitionen av avancerad teknologi bör avgränsas utifrån objektiva tekniska specifikationer som är anpassade efter riskbilden, och tar hänsyn till särskilda ägarfördelar för EU-företag utomlands och av att ta fram objektiva kriterier för att identifiera relevanta tredjeländer. </span>\r\n\t\t\t</p>\r\n\t\t\t<p class=\"NormalIndent\">\r\n\t\t\t\t<span>I ljuset av Kommerskollegiums observationer vill utskottet understryka vikten av att noga överväga införandet och utformningen av regelverk för utgående investeringar, för att säkerställa att dessa inte stjälper mer än de hjälper. Utskottet vill även betona vikten av en metodisk och försiktig inställning till införandet av nya övervakningsmekanismer. Det är, enligt utskottets uppfattning, viktigt att säkerställa att eventuella åtgärder är proportionerliga mot de identifierade riskerna och att de administrativa kostnaderna och bördorna för medlemsstaterna och näringslivet är motiverade i förhållande till de förväntade säkerhetsfördelarna. Utskottet menar att det är avgörande att Sverige och EU överväger dessa aspekter för att försäkra att eventuella nya regelverk stöder en hållbar och konkurrenskraftig framtida utveckling av den svenska och europeiska ekonomin samtidigt som man säkerställer att känsliga teknologier eller kunskap inte faller i orätta händer. Utskottet står även bakom Kommerskollegiums ovan nämnda rekommen</span><span>­</span><span>dationer för det fortsatta arbetet. </span>\r\n\t\t\t</p>\r\n\t\t\t<p class=\"NormalIndent\">\r\n\t\t\t\t<span>Sammanfattningsvis anser utskottet att det är viktigt att förstå och analysera risker samt möjligheter med utgående investeringar, innan det går att ta ställning till ett eventuellt behov av att vidta nya åtgärder. Det är särskilt viktigt att förstå och analysera risker och möjligheter med strategiskt skyddsvärd teknologi och kunskap. Det tillvägagångssätt som kommissionen rekom</span><span>­</span><span>menderar med införandet av en övervakning av utgående investeringar skulle kunna vara ett av flera sätt att få information. Behovet och lämpligheten av övervakning av utgående investeringar måste dock analyseras och övervägas med försiktighet. En avvägning behövs huruvida en övervakning av utgående investeringar är proportionerlig och om kostnaderna och den ad</span><span>­</span><span>min</span><span>­</span><span>­</span><span>­</span><span>istrativa bördan för medlemsstaterna och företagen kan motiveras i förhållande till syftet. Medlemsstaternas fördragsfästa ansvar för nationell säkerhet måste enligt utskottets uppfattning säkerställas i förhållande till den information som förutses delas med kommissionen.</span><span style=\"-aw-bookmark-end:_Hlk165294540\"></span><span> Med anledning av det pågående arbete på EU-nivå inom området för att stärka ett effektivt och proportionerligt granskningssystem avser utskottet att noga följa utvecklingen framöver. </span>\r\n\t\t\t</p>\r\n\t\t\t<p class=\"NormalIndent\">\r\n\t\t\t\t<span>Därmed föreslår utskottet att riksdagen lägger utlåtandet till handlingarna.</span>\r\n\t\t\t</p>\r\n\t\t\t<p>\r\n\t\t\t\t<span style=\"-aw-import:ignore\"> </span>\r\n\t\t\t</p>\r\n\t\t\t<p class=\"Avsnittsrubrik\">\r\n\t\t\t\t<a name=\"_Toc166749283\"><span class=\"tSidrubrikJA\">Reservation</span></a>\r\n\t\t\t</p>\r\n\t\t\t<div style=\"-aw-sdt-tag:'539dd99f-ba00-48f9-90d6-e3ec5196c126/reservationer/-1126567326/1715849620087'; -aw-sdt-title:'reservationer'\">\r\n\t\t\t\t<p class=\"Mellanrum\">\r\n\t\t\t\t\t<span style=\"-aw-import:ignore\"> </span>\r\n\t\t\t\t</p>\r\n\t\t\t\t<table cellspacing=\"0\" cellpadding=\"0\" style=\"width:294.2pt; margin-top:0pt; border-collapse:collapse\">\r\n\t\t\t\t\t<tr style=\"page-break-inside:avoid\">\r\n\t\t\t\t\t\t<td style=\"vertical-align:top\">\r\n\t\t\t\t\t\t\t<p class=\"Reservationsrubrik\">\r\n\t\t\t\t\t\t\t\t<a name=\"_Toc166749284\"><span>Kommissionens vitbok om utgående investeringar – motiveringen (V, MP)</span></a>\r\n\t\t\t\t\t\t\t</p>\r\n\t\t\t\t\t\t</td>\r\n\t\t\t\t\t</tr>\r\n\t\t\t\t</table>\r\n\t\t\t\t<p class=\"Normalutanluftfre\">\r\n\t\t\t\t\t<span>av Lorena Delgado Varas (V) och Linus Lakso (MP).</span>\r\n\t\t\t\t</p>\r\n\t\t\t\t<p class=\"Mellanrum\">\r\n\t\t\t\t\t<span style=\"-aw-import:ignore\"> </span>\r\n\t\t\t\t</p>\r\n\t\t\t\t<p class=\"Mellanrum\">\r\n\t\t\t\t\t<span style=\"-aw-import:ignore\"> </span>\r\n\t\t\t\t</p>\r\n\t\t\t</div>\r\n\t\t\t<p class=\"R4\">\r\n\t\t\t\t<span>Ställningstagande</span>\r\n\t\t\t</p>\r\n\t\t\t<p>\r\n\t\t\t\t<span>Som redogjorts för inledningsvis i detta utlåtande innehåller kommissionens vitbok en inriktning för det fortsatta arbetet med utgående investeringar och de risker som dessa investeringar kan innebära till följd av att teknik eller kunskap hamnar i fel händer. Eftersom det i dagsläget råder en informationsbrist om vilka utgående investeringar som görs från EU till länder utanför unionen presenterar kommissionen en stegvis ansats. </span>\r\n\t\t\t</p>\r\n\t\t\t<p class=\"NormalIndent\">\r\n\t\t\t\t<span>Vi vill med anledning av vitboken inledningsvis redogöra för vår syn på handel och investeringar. Enligt vår mening behöver de åtgärder som vidtas inom området handel och investeringar alltid utformas med hänsyn till miljön, klimatet och de mänskliga rättigheterna. För att handel och investeringar ska kunna ske på rättvisa villkor måste man låta fattiga länder få fördelar och större utrymme att utforma sin egen politik. Handel och investeringar ska också vara verktyg för att dela med sig av grön teknik och uppmuntra länder att stärka sin klimat- och miljöpolitik. I detta sammanhang vill vi även påpeka att oreglerad och okritiskt främjad internationell handel och investeringar kan leda till negativa konsekvenser för miljön och samhällen. Det inkluderar risker som överutnyttjande av naturresurser, förstörelse av biologisk mångfald och undergrävande av lokala samhällens rättigheter och levnadsvillkor. </span>\r\n\t\t\t</p>\r\n\t\t\t<p class=\"NormalIndent\">\r\n\t\t\t\t<span>Vi motsätter oss också en politik som prioriterar ekonomiska intressen framför att upprätthålla höga miljö- och arbetsstandarder. En hållbar handels- och investeringspolitik bör inte enbart fokusera på att minska administrativa bördor utan också på att stärka miljömässiga och sociala kriterier i internationella avtal. Samtidigt menar vi att det är viktigt att förhindra att handel och investeringar blir verktyg för exploatering snarare än medel för verklig global utveckling. Vi vill betona vikten av att integrera hållbarhets</span><span>­</span><span>principer i alla handels- och investeringsbeslut för att säkerställa att de inte enbart gynnar ekonomisk tillväxt utan också främjar en rättvis och hållbar utveckling globalt.</span>\r\n\t\t\t</p>\r\n\t\t\t<p class=\"NormalIndent\">\r\n\t\t\t\t<span>Mot denna bakgrund vill vi framföra vår uppfattning att det är av väsentlig betydelse att ett system med granskning av utgående investeringar inte försvårar en hållbar global klimatomställning. Det innebär att ett gransknings</span><span>­</span><span>system bör utformas så att det inte begränsar eller hämmar utbyte av grön teknik och smarta innovationer, inte minst när det gäller det globala syd.</span><span style=\"-aw-import:spaces\">  </span>\r\n\t\t\t</p>\r\n\t\t\t<p class=\"NormalIndent\">\r\n\t\t\t\t<span>Vi noterar de observationer och synpunkter som Kommerskollegium och Svenskt Näringsliv har gjort gällande det som förs fram i kommissionens vitbok. Kommerskollegium har bl.a. pekat på de risker och utmaningar som ett strikt granskningssystem för utgående investeringar kan medföra. Utredningen belyser bekymmer om att ett omfattande och rigitt system kan försvåra för svenska företags möjligheter att agera fritt på internationella arenor, vilket potentiellt kan leda till negativa ekonomiska konsekvenser för Sverige. Dessa risker inkluderar en ökad administrativ börda och potentiella förseningar i genomförandet av gränsöverskridande affärstransaktioner. Utredningen diskuterar även risken att sådana system kan missbrukas för protektionistiska ändamål, vilket skulle kunna underminera den svenska öppna marknadsekonomin. Med anledning av de observationer och synpunkter som har framförts vill vi framföra vår uppfattning att omfattningen av och detaljnivån på informationen som samlas in bör begränsas för att minimera administrativ börda för såväl företag som myndigheter. Av detta skäl anser vi att datainsamling i första hand bör baseras på offentligt tillgängliga uppgifter. Vidare är det angeläget, såsom Kommerskollegium framfört, att det utformas objektiva kriterier för att identifiera relevanta tredjeländer för att länder i det globala syd inte ska drabbas i onödan.</span><span style=\"-aw-import:spaces\">  </span>\r\n\t\t\t</p>\r\n\t\t\t<p class=\"NormalIndent\">\r\n\t\t\t\t<span>Även om kommissionens vitbok riktar in sig mot utgående investeringar som företag gör vill vi i detta sammanhang framhålla nödvändigheten av att värna om den akademiska friheten. Det är angeläget att åtgärder inte oavsiktligt inskränker möjligheterna till fri forskning och internationellt vetenskapligt utbyte. Sverige har etablerat sig som en stark forskningsnation, inte bara genom högkvalitativa forskningsresultat, utan även genom sitt globala samarbete och utbyte av kunskap. Det internationella samarbetet, som är avgörande för vetenskapliga framsteg och innovation, måste fortsätta att stödjas och främjas. Man behöver därför vara vaksam så att de säkerhets</span><span>­</span><span>åtgärder som genomförs inte hindrar forskare från att fritt utbyta idéer och samarbeta över gränserna. Vi noterar att Universitets- och högskolerådet, Vetenskapsrådet och Vinnova har fått i uppdrag att granska frågor om internationellt forskningssamarbete. Det är viktigt att deras arbete inkluderar en noggrann utvärdering av hur säkerhetsåtgärder kan genomföras utan att störa den akademiska friheten. Balansen mellan säkerhet och frihet är avgörande, och det är viktigt att de åtgärder som övervägs inte endast skyddar känslig teknologi och kunskap utan också stöder och upprätthåller en miljö där akademisk frihet kan utvecklas.</span>\r\n\t\t\t</p>\r\n\t\t\t<p class=\"NormalIndent\">\r\n\t\t\t\t<span>Slutligen vill vi framhålla vår uppfattning om att den övergripande målsätt</span><span>­</span><span>ningen för att säkra EU:s ekonomiska intressen och teknologiska suveränitet, och det övervakningssystem som förs fram, brister i dess omfattning genom att inte inkludera utgående fossila investeringar. Investeringar i fossila bränslen som görs i tredjeländer kan innebära betydande miljömässiga, sociala och politiska risker, vilket i sin tur kan påverka EU:s långsiktiga hållbarhets- och säkerhetsmål. Det är avgörande att dessa investeringar granskas med samma noggrannhet som investeringar inom avancerade halvledare, artificiell intelligens, kvantteknik och bioteknik. Vi menar därför att övervaknings</span><span>­</span><span>systemet som presenteras i vitboken bör utvidgas för att även inkludera systematisk granskning av utgående investeringar inom fossila bränslen. Detta skulle ge en mer heltäckande bild av EU:s externa ekonomiska aktiviteter och bidra till en mer hållbar och säker framtid. </span>\r\n\t\t\t</p>\r\n\t\t\t<p class=\"NormalIndent\">\r\n\t\t\t\t<span>Därmed föreslår vi att riksdagen lägger utlåtandet till handlingarna.</span>\r\n\t\t\t</p>\r\n\t\t\t<p>\r\n\t\t\t\t<span style=\"-aw-import:ignore\"> </span>\r\n\t\t\t</p>\r\n\t\t\t<p>\r\n\t\t\t\t<span style=\"-aw-import:ignore\"> </span>\r\n\t\t\t</p>\r\n\t\t\t<p class=\"Bilaga\">\r\n\t\t\t\t<span class=\"tBilagaJA\" style=\"text-decoration:underline\">Bilaga</span>\r\n\t\t\t</p>\r\n\t\t\t<p class=\"Bilagerubrik\">\r\n\t\t\t\t<a name=\"_Toc166749285\"><span class=\"tSidrubrikJA\">Förteckning över granskade dokument</span></a>\r\n\t\t\t</p>\r\n\t\t\t<p>\r\n\t\t\t\t<span style=\"font-style:italic\">Kommissionens vitbok om utgående investeringar (COM(2024) 24</span>\r\n\t\t\t</p>\r\n\t\t\t<p class=\"NormalIndent\" style=\"text-indent:0pt\">\r\n\t\t\t\t<span style=\"-aw-import:ignore\"> </span>\r\n\t\t\t</p>\r\n\t\t\t<p class=\"Mellanrum\">\r\n\t\t\t\t<span style=\"-aw-import:ignore\"> </span>\r\n\t\t\t</p>\r\n\t\t</div>\r\n\t"},"dokutskottsforslag":{"utskottsforslag":{"punkt":"1","rubrik":"Kommissionens vitbok om utgående investeringar","forslag":"Riksdagen l&auml;gger utl&aring;tandet till handlingarna.&#160;<BR/><BR/><BR/>","beslutstyp":"acklamation","motforslag_nummer":"0","motforslag_partier":null,"votering_id":null,"votering_sammanfattning_html":null,"votering_url_xml":null,"rm":"2023/24","bet":"NU20","vinnare":"utskottet","voteringskrav":null,"beslutsregelkvot":null,"beslutsregelparagraf":null,"punkttyp":null}},"dokmotforslag":{"motforslag":{"nummer":"1","rubrik":null,"partier":"\"V\",\"MP\"","typ":"reservation","utskottsforslag_punkt":"1"}},"dokaktivitet":{"aktivitet":[{"kod":"UBE","namn":"Beredning","datum":"2024-04-16 00:00:00","status":"inträffat","ordning":"0","process":null},{"kod":"UBE","namn":"Beredning","datum":"2024-05-07 00:00:00","status":"inträffat","ordning":"0","process":null},{"kod":"JUS","namn":"Justering","datum":"2024-05-16 00:00:00","status":"inträffat","ordning":"0","process":null},{"kod":"TRY","namn":"Trycklov","datum":"2024-05-16 00:00:00","status":"inträffat","ordning":"0","process":null},{"kod":"B","namn":"Bordläggning","datum":"2024-05-21 00:00:00","status":"inträffat","ordning":"0","process":null},{"kod":"BEH","namn":"Behandling","datum":"2024-05-22 00:00:00","status":"inträffat","ordning":"0","process":null},{"kod":"BES","namn":"Beslut","datum":"2024-05-22 00:00:00","status":"inträffat","ordning":"0","process":null}]},"dokuppgift":{"uppgift":[{"kod":"arendestatuskammaren","namn":"Beslutat","text":null,"dok_id":"HB01NU20","systemdatum":"2024-05-22 16:40:44"},{"kod":"beslutssammanfattningusk","namn":"Utskottets förslag till beslut","text":"Utlåtandet läggs till handlingarna.","dok_id":"HB01NU20","systemdatum":"2024-06-25 11:30:45"},{"kod":"rdbeslut","namn":"Riksdagens beslut","text":"Kammaren biföll utskottets förslag.","dok_id":"HB01NU20","systemdatum":"2024-05-22 16:40:44"},{"kod":"beslutdatumtid","namn":"Datum och tid för beslutet","text":"2024-05-22 00:00:00","dok_id":"HB01NU20","systemdatum":"2024-05-22 16:49:09"},{"kod":"debattdatumtid","namn":"Datum och tid för debatten","text":"2024-05-22 00:00:00","dok_id":"HB01NU20","systemdatum":"2024-05-22 16:49:09"},{"kod":"notis","namn":"Beslut i korthet","text":"<p>Riksdagen har granskat EU-kommissionens vitbok om utgående investeringar, det vill säga investeringar som görs i verksamheter utanför EU. I vitboken, som är en typ av idédokument, bedömer kommissionen att det kan finnas skäl att se över riskerna för att kunskap och teknik hamnar i fel händer vid utgående investeringar. Medlemsstaterna rekommenderas att lägga fokus på fyra känsliga teknikområden:</p>\r\n<ul>\r\n<li>avancerade halvledare</li>\r\n<li>artificiell intelligens</li>\r\n<li>kvantteknik</li>\r\n<li>bioteknik.</li>\r\n</ul>\r\n<p>För att hantera de risker som identifieras rekommenderar kommissionen bland annat en övervakningsprocess för medlemsstaterna.</p>\r\n<p>Riksdagen instämmer i att riskerna med utgående investeringar kan behöva ses över och menar att övervakningsprocessen skulle kunna vara ett av flera tillvägagångssätt. Samtidigt behöver åtgärderna vara proportionerliga för att upprätthålla konkurrenskraften i den svenska och europeiska ekonomin. Därför bör idéerna som förs fram i vitboken noggrant granskas och utvärderas när det gäller risker och möjligheter.</p>\r\n<p>Riksdagen beslutade att lägga utskottets utlåtande om kommissionens vitbok till handlingarna, det vill säga avsluta ärendet.</p>","dok_id":"HB01NU20","systemdatum":"2024-05-22 16:49:09"},{"kod":"notisrubrik","namn":"Beslut","text":"Idédokument om säkrare investeringar utanför EU har granskats (NU20)","dok_id":"HB01NU20","systemdatum":"2024-05-22 16:49:09"},{"kod":"statustext","namn":"statustext","text":"Ärendet är avslutat","dok_id":"HB01NU20","systemdatum":"2024-05-23 00:15:27"},{"kod":"utsknotis","namn":"Utskottets förslag till beslut","text":"<p>Näringsutskottet har granskat EU-kommissionens vitbok om utgående investeringar, det vill säga investeringar som görs i verksamheter utanför EU. I vitboken, som är en typ av idédokument, bedömer kommissionen att det kan finnas skäl att se över riskerna för att kunskap och teknik hamnar i fel händer vid utgående investeringar. Medlemsstaterna rekommenderas att lägga fokus på fyra känsliga teknikområden:</p>\r\n<ul>\r\n<li>avancerade halvledare</li>\r\n<li>artificiell intelligens</li>\r\n<li>kvantteknik</li>\r\n<li>bioteknik.</li>\r\n</ul>\r\n<p>För att hantera de risker som identifieras rekommenderar kommissionen bland annat en övervakningsprocess för medlemsstaterna.</p>\r\n<p>Näringsutskottet instämmer i att riskerna med utgående investeringar kan behöva ses över och menar att övervakningsprocessen skulle kunna vara ett av flera tillvägagångssätt. Samtidigt behöver åtgärderna vara proportionerliga för att upprätthålla konkurrenskraften i den svenska och europeiska ekonomin. Därför bör idéerna som förs fram i vitboken noggrant granskas och utvärderas när det gäller risker och möjligheter.</p>\r\n<p>Utskottet föreslår att riksdagen ska lägga utskottets utlåtande om kommissionens vitbok till handlingarna, det vill säga avsluta ärendet.</p>","dok_id":"HB01NU20","systemdatum":"2024-05-22 16:49:09"},{"kod":"utsknotisrubrik","namn":"Utskottets förslag","text":"Idédokument om säkrare investeringar utanför EU har granskats (NU20)","dok_id":"HB01NU20","systemdatum":"2024-05-22 16:49:09"}]},"dokbilaga":{"bilaga":{"dok_id":"HB01NU20","subtitel":null,"filnamn":"2023_24_NU20_20240516162319_Publicering.pdf","filstorlek":"226756","filtyp":"pdf","titel":"Kommissionens vitbok om utgående investeringar","fil_url":"https://data.riksdagen.se/fil/75CFE1DA-3763-4C40-A6F5-60F465504C01"}},"dokreferens":{"referens":[{"referenstyp":"beslut_id","uppgift":"Beslut 2023/24:NU20","ref_dok_id":"HBC320240522NU20","ref_dok_typ":"kammakt","ref_dok_rm":"2023/24","ref_dok_bet":"NU20","ref_dok_titel":"Beslut: Kommissionens vitbok om utgående investeringar","ref_dok_subtitel":null,"ref_dok_subtyp":"vo","ref_dok_dokumentnamn":"Votering"},{"referenstyp":"föredragningslista","uppgift":"föredragningslista 2023/24:119 Onsdag den 22 maj 2024","ref_dok_id":"HB0I119","ref_dok_typ":"f-lista","ref_dok_rm":"2023/24","ref_dok_bet":"119","ref_dok_titel":"Onsdag den 22 maj 2024","ref_dok_subtitel":null,"ref_dok_subtyp":null,"ref_dok_dokumentnamn":"Kammarens föredragningslistor"},{"referenstyp":"protokollbeslut","uppgift":"2024-05-22","ref_dok_id":"HB09119","ref_dok_typ":"prot","ref_dok_rm":"2023/24","ref_dok_bet":"119","ref_dok_titel":"Protokoll 2023/24:119 Onsdagen den 22 maj","ref_dok_subtitel":null,"ref_dok_subtyp":null,"ref_dok_dokumentnamn":"Protokoll"}]},"webbmedia":{"media":{"url":"VOD1/HD/2442405220041736221","videofileurl":"https://mamstream.riksdagen.se/VOD1/_definst_/smil:HD/2442405220041736221.smil/playlist.m3u8","audiofileurl":"https://mhdownload.riksdagen.se/VOD1/HD/2442405220041736221_aud.mp3","downloadurl":"https://mhdownload.riksdagen.se/VOD1/HD/2442405220041736221_720p.mp4","thumbnailurl":"https://mhdownload.riksdagen.se/posterframe/2442405220041736221.jpg","debateurl":"/sv/webb-tv/video/debatt-om-forslag/kommissionens-vitbok-om-utgaende-investeringar_HB01NU20","debattsekunder":"12","debatt_rm":"2023/24","debatt_typ":"Arbetsplenum","dok_beteckning":"NU20","datum":"2024-05-22 15:33:48","dok_id":"HB01NU20","videostatus":"2","source":"Rim","inspelningstyp":"Kammarsystemet","systemdatum":"2024-05-22 15:36:06"}}}}