{"dokumentstatus":{"dokument":{"hangar_id":"5272627","dok_id":"HD01MJU11","rm":"2025/26","beteckning":"MJU11","typ":"bet","subtyp":"bet","doktyp":"bet","typrubrik":"Betänkande 2025/26:MJU11","dokumentnamn":"Betänkande","debattnamn":"Debatt om förslag","tempbeteckning":null,"organ":"MJU","mottagare":null,"nummer":"11","slutnummer":"0","datum":"2025-11-12 00:00:00","systemdatum":"2025-12-03 14:34:20","publicerad":"2025-11-12 16:09:52","titel":"Fiskeripolitik","subtitel":null,"status":"planerat","htmlformat":null,"relaterat_id":null,"source":"Brus","sourceid":"beb96e0c-704d-4905-ad90-9cf106d2fb14","metadata":null,"dokument_url_text":"https://data.riksdagen.se/dokument/HD01MJU11/text","dokument_url_html":"https://data.riksdagen.se/dokument/HD01MJU11","dokumentstatus_url_xml":"https://data.riksdagen.se/dokumentstatus/HD01MJU11","utskottsforslag_url_xml":"https://data.riksdagen.se/utskottsforslag/HD01MJU11","html":"<h2>Fiskeripolitik</h2>\r\nDokumentet är inte publicerat"},"dokaktivitet":{"aktivitet":[{"kod":"UBE","namn":"Beredning","datum":"2026-01-20 00:00:00","status":"planerat","ordning":"0","process":null},{"kod":"UBE","namn":"Beredning","datum":"2026-02-05 00:00:00","status":"planerat","ordning":"0","process":null},{"kod":"JUS","namn":"Justering","datum":"2026-02-19 00:00:00","status":"planerat","ordning":"0","process":null},{"kod":"TRY","namn":"Trycklov","datum":"2026-02-20 00:00:00","status":"planerat","ordning":"0","process":null},{"kod":"B","namn":"Bordläggning","datum":"2026-02-25 00:00:00","status":"planerat","ordning":"0","process":null},{"kod":"BEH","namn":"Behandling","datum":"2026-02-26 00:00:00","status":"planerat","ordning":"0","process":null},{"kod":"BES","namn":"Beslut","datum":"2026-03-04 00:00:00","status":"planerat","ordning":"0","process":null}]},"dokreferens":{"referens":[{"referenstyp":"behandlar","uppgift":"motion 2025/26:1300 Bevarande av ålfisket","ref_dok_id":"HD021300","ref_dok_typ":"mot","ref_dok_rm":"2025/26","ref_dok_bet":"1300","ref_dok_titel":"Bevarande av ålfisket","ref_dok_subtitel":"av Björn Söder m.fl. (SD)","ref_dok_subtyp":"mot","ref_dok_dokumentnamn":"Motion"},{"referenstyp":"behandlar","uppgift":"motion 2025/26:1332 Flodkräftans bevarande","ref_dok_id":"HD021332","ref_dok_typ":"mot","ref_dok_rm":"2025/26","ref_dok_bet":"1332","ref_dok_titel":"Flodkräftans bevarande","ref_dok_subtitel":"av Runar Filper (SD)","ref_dok_subtyp":"mot","ref_dok_dokumentnamn":"Motion"},{"referenstyp":"behandlar","uppgift":"motion 2025/26:1660 Livskraftig skånsk landsbygd","ref_dok_id":"HD021660","ref_dok_typ":"mot","ref_dok_rm":"2025/26","ref_dok_bet":"1660","ref_dok_titel":"Livskraftig skånsk landsbygd","ref_dok_subtitel":"av Peter Ollén m.fl. (M)","ref_dok_subtyp":"mot","ref_dok_dokumentnamn":"Motion"},{"referenstyp":"behandlar","uppgift":"motion 2025/26:1666 Förbud mot storskaligt fiske och bottentrålning","ref_dok_id":"HD021666","ref_dok_typ":"mot","ref_dok_rm":"2025/26","ref_dok_bet":"1666","ref_dok_titel":"Förbud mot storskaligt fiske och bottentrålning","ref_dok_subtitel":"av Carl Nordblom m.fl. (M)","ref_dok_subtyp":"mot","ref_dok_dokumentnamn":"Motion"},{"referenstyp":"behandlar","uppgift":"motion 2025/26:1722 Regional fiskeförvaltning","ref_dok_id":"HD021722","ref_dok_typ":"mot","ref_dok_rm":"2025/26","ref_dok_bet":"1722","ref_dok_titel":"Regional fiskeförvaltning","ref_dok_subtitel":"av Marie Nicholson (M)","ref_dok_subtyp":"mot","ref_dok_dokumentnamn":"Motion"},{"referenstyp":"behandlar","uppgift":"motion 2025/26:1737 Fiskevårdskort för fritidsfiske i Östersjön","ref_dok_id":"HD021737","ref_dok_typ":"mot","ref_dok_rm":"2025/26","ref_dok_bet":"1737","ref_dok_titel":"Fiskevårdskort för fritidsfiske i Östersjön","ref_dok_subtitel":"av Marie Nicholson (M)","ref_dok_subtyp":"mot","ref_dok_dokumentnamn":"Motion"},{"referenstyp":"behandlar","uppgift":"motion 2025/26:1907 Ett system med fisketillsyningspersoner även längs med kusterna","ref_dok_id":"HD021907","ref_dok_typ":"mot","ref_dok_rm":"2025/26","ref_dok_bet":"1907","ref_dok_titel":"Ett system med fisketillsyningspersoner även längs med kusterna","ref_dok_subtitel":"av Magnus Manhammar (S)","ref_dok_subtyp":"mot","ref_dok_dokumentnamn":"Motion"},{"referenstyp":"behandlar","uppgift":"motion 2025/26:1911 Ekosystembaserad havsförvaltning","ref_dok_id":"HD021911","ref_dok_typ":"mot","ref_dok_rm":"2025/26","ref_dok_bet":"1911","ref_dok_titel":"Ekosystembaserad havsförvaltning","ref_dok_subtitel":"av Magnus Manhammar (S)","ref_dok_subtyp":"mot","ref_dok_dokumentnamn":"Motion"},{"referenstyp":"behandlar","uppgift":"motion 2025/26:2108 Bottennära fiske","ref_dok_id":"HD022108","ref_dok_typ":"mot","ref_dok_rm":"2025/26","ref_dok_bet":"2108","ref_dok_titel":"Bottennära fiske","ref_dok_subtitel":"av Sten Bergheden (M)","ref_dok_subtyp":"mot","ref_dok_dokumentnamn":"Motion"},{"referenstyp":"behandlar","uppgift":"motion 2025/26:2286 Åtgärder för att nå en långsiktigt hållbar fiskeripolitik i Östersjön","ref_dok_id":"HD022286","ref_dok_typ":"mot","ref_dok_rm":"2025/26","ref_dok_bet":"2286","ref_dok_titel":"Åtgärder för att nå en långsiktigt hållbar fiskeripolitik i Östersjön","ref_dok_subtitel":"av Linnéa Wickman m.fl. (S)","ref_dok_subtyp":"mot","ref_dok_dokumentnamn":"Motion"},{"referenstyp":"behandlar","uppgift":"motion 2025/26:2465 Bevarande av ålfisket som ett kulturarv","ref_dok_id":"HD022465","ref_dok_typ":"mot","ref_dok_rm":"2025/26","ref_dok_bet":"2465","ref_dok_titel":"Bevarande av ålfisket som ett kulturarv","ref_dok_subtitel":"av Ludvig Ceimertz m.fl. (M)","ref_dok_subtyp":"mot","ref_dok_dokumentnamn":"Motion"},{"referenstyp":"behandlar","uppgift":"motion 2025/26:2506 Strömmingsbestånden","ref_dok_id":"HD022506","ref_dok_typ":"mot","ref_dok_rm":"2025/26","ref_dok_bet":"2506","ref_dok_titel":"Strömmingsbestånden","ref_dok_subtitel":"av Jesper Skalberg Karlsson m.fl. (M)","ref_dok_subtyp":"mot","ref_dok_dokumentnamn":"Motion"},{"referenstyp":"behandlar","uppgift":"motion 2025/26:2510 Fisket i Skåne","ref_dok_id":"HD022510","ref_dok_typ":"mot","ref_dok_rm":"2025/26","ref_dok_bet":"2510","ref_dok_titel":"Fisket i Skåne","ref_dok_subtitel":"av Ann-Charlotte Hammar Johnsson m.fl. (M)","ref_dok_subtyp":"mot","ref_dok_dokumentnamn":"Motion"},{"referenstyp":"behandlar","uppgift":"motion 2025/26:2512 Det industriella trålfisket i Östersjön","ref_dok_id":"HD022512","ref_dok_typ":"mot","ref_dok_rm":"2025/26","ref_dok_bet":"2512","ref_dok_titel":"Det industriella trålfisket i Östersjön","ref_dok_subtitel":"av Kjell Jansson m.fl. (M)","ref_dok_subtyp":"mot","ref_dok_dokumentnamn":"Motion"},{"referenstyp":"behandlar","uppgift":"motion 2025/26:2617 Stärkande av det svenska vattenbruket","ref_dok_id":"HD022617","ref_dok_typ":"mot","ref_dok_rm":"2025/26","ref_dok_bet":"2617","ref_dok_titel":"Stärkande av det svenska vattenbruket","ref_dok_subtitel":"av Rickard Nordin (C)","ref_dok_subtyp":"mot","ref_dok_dokumentnamn":"Motion"},{"referenstyp":"behandlar","uppgift":"motion 2025/26:2659 Det småskaliga kustnära fisket efter Norrlandskusten","ref_dok_id":"HD022659","ref_dok_typ":"mot","ref_dok_rm":"2025/26","ref_dok_bet":"2659","ref_dok_titel":"Det småskaliga kustnära fisket efter Norrlandskusten","ref_dok_subtitel":"av Anders W Jonsson (C)","ref_dok_subtyp":"mot","ref_dok_dokumentnamn":"Motion"},{"referenstyp":"behandlar","uppgift":"motion 2025/26:2776 Västafrika och Västsahara","ref_dok_id":"HD022776","ref_dok_typ":"mot","ref_dok_rm":"2025/26","ref_dok_bet":"2776","ref_dok_titel":"Västafrika och Västsahara","ref_dok_subtitel":"av Håkan Svenneling m.fl. (V)","ref_dok_subtyp":"mot","ref_dok_dokumentnamn":"Motion"},{"referenstyp":"behandlar","uppgift":"motion 2025/26:2784 Biologisk mångfald","ref_dok_id":"HD022784","ref_dok_typ":"mot","ref_dok_rm":"2025/26","ref_dok_bet":"2784","ref_dok_titel":"Biologisk mångfald","ref_dok_subtitel":"av Nooshi Dadgostar m.fl. (V)","ref_dok_subtyp":"mot","ref_dok_dokumentnamn":"Motion"},{"referenstyp":"behandlar","uppgift":"motion 2025/26:2824 Natur och biologisk mångfald","ref_dok_id":"HD022824","ref_dok_typ":"mot","ref_dok_rm":"2025/26","ref_dok_bet":"2824","ref_dok_titel":"Natur och biologisk mångfald","ref_dok_subtitel":"av Stina Larsson m.fl. (C)","ref_dok_subtyp":"mot","ref_dok_dokumentnamn":"Motion"},{"referenstyp":"behandlar","uppgift":"motion 2025/26:2825 Vatten, hav och fiske","ref_dok_id":"HD022825","ref_dok_typ":"mot","ref_dok_rm":"2025/26","ref_dok_bet":"2825","ref_dok_titel":"Vatten, hav och fiske","ref_dok_subtitel":"av Stina Larsson m.fl. (C)","ref_dok_subtyp":"mot","ref_dok_dokumentnamn":"Motion"},{"referenstyp":"behandlar","uppgift":"motion 2025/26:2849 Satsning på Stockholms skärgård","ref_dok_id":"HD022849","ref_dok_typ":"mot","ref_dok_rm":"2025/26","ref_dok_bet":"2849","ref_dok_titel":"Satsning på Stockholms skärgård","ref_dok_subtitel":"av Markus Wiechel (SD)","ref_dok_subtyp":"mot","ref_dok_dokumentnamn":"Motion"},{"referenstyp":"behandlar","uppgift":"motion 2025/26:2905 Blå näringens betydelse för Västsverige","ref_dok_id":"HD022905","ref_dok_typ":"mot","ref_dok_rm":"2025/26","ref_dok_bet":"2905","ref_dok_titel":"Blå näringens betydelse för Västsverige","ref_dok_subtitel":"av Jennie Wernäng (M)","ref_dok_subtyp":"mot","ref_dok_dokumentnamn":"Motion"},{"referenstyp":"behandlar","uppgift":"motion 2025/26:3088 En levande och välmående skärgård","ref_dok_id":"HD023088","ref_dok_typ":"mot","ref_dok_rm":"2025/26","ref_dok_bet":"3088","ref_dok_titel":"En levande och välmående skärgård","ref_dok_subtitel":"av Markus Wiechel och Göran Hargestam (båda SD)","ref_dok_subtyp":"mot","ref_dok_dokumentnamn":"Motion"},{"referenstyp":"behandlar","uppgift":"motion 2025/26:3285 Östersjön och Blekinges fiske","ref_dok_id":"HD023285","ref_dok_typ":"mot","ref_dok_rm":"2025/26","ref_dok_bet":"3285","ref_dok_titel":"Östersjön och Blekinges fiske","ref_dok_subtitel":"av Camilla Brunsberg (M)","ref_dok_subtyp":"mot","ref_dok_dokumentnamn":"Motion"},{"referenstyp":"behandlar","uppgift":"motion 2025/26:3444 Blåfenad tonfisk är blå tillväxt","ref_dok_id":"HD023444","ref_dok_typ":"mot","ref_dok_rm":"2025/26","ref_dok_bet":"3444","ref_dok_titel":"Blåfenad tonfisk är blå tillväxt","ref_dok_subtitel":"av Ann-Sofie Alm (M)","ref_dok_subtyp":"mot","ref_dok_dokumentnamn":"Motion"},{"referenstyp":"behandlar","uppgift":"motion 2025/26:3596 En folkrörelse för klimatet","ref_dok_id":"HD023596","ref_dok_typ":"mot","ref_dok_rm":"2025/26","ref_dok_bet":"3596","ref_dok_titel":"En folkrörelse för klimatet","ref_dok_subtitel":"av Elisabeth Thand Ringqvist m.fl. (C)","ref_dok_subtyp":"mot","ref_dok_dokumentnamn":"Motion"},{"referenstyp":"behandlar","uppgift":"motion 2025/26:3732 Utgiftsområde 20 Klimat, miljö och natur","ref_dok_id":"HD023732","ref_dok_typ":"mot","ref_dok_rm":"2025/26","ref_dok_bet":"3732","ref_dok_titel":"Utgiftsområde 20 Klimat, miljö och natur","ref_dok_subtitel":"av Åsa Westlund m.fl. (S)","ref_dok_subtyp":"mot","ref_dok_dokumentnamn":"Motion"},{"referenstyp":"behandlar","uppgift":"motion 2025/26:3733 Utgiftsområde 23 Areella näringar, landsbygd och livsmedel","ref_dok_id":"HD023733","ref_dok_typ":"mot","ref_dok_rm":"2025/26","ref_dok_bet":"3733","ref_dok_titel":"Utgiftsområde 23 Areella näringar, landsbygd och livsmedel","ref_dok_subtitel":"av Åsa Westlund m.fl. (S)","ref_dok_subtyp":"mot","ref_dok_dokumentnamn":"Motion"},{"referenstyp":"behandlar","uppgift":"motion 2025/26:3774 Levande hav och vatten","ref_dok_id":"HD023774","ref_dok_typ":"mot","ref_dok_rm":"2025/26","ref_dok_bet":"3774","ref_dok_titel":"Levande hav och vatten","ref_dok_subtitel":"av Emma Nohrén m.fl. (MP)","ref_dok_subtyp":"mot","ref_dok_dokumentnamn":"Motion"},{"referenstyp":"behandlar","uppgift":"motion 2025/26:394 Reglerad undervattensjakt - balans mellan fritid och natur","ref_dok_id":"HD02394","ref_dok_typ":"mot","ref_dok_rm":"2025/26","ref_dok_bet":"394","ref_dok_titel":"Reglerad undervattensjakt - balans mellan fritid och natur","ref_dok_subtitel":"av Magnus Berntsson (KD)","ref_dok_subtyp":"mot","ref_dok_dokumentnamn":"Motion"},{"referenstyp":"behandlar","uppgift":"motion 2025/26:395 Yrkesfiskets betydelse för Sveriges försörjningsförmåga","ref_dok_id":"HD02395","ref_dok_typ":"mot","ref_dok_rm":"2025/26","ref_dok_bet":"395","ref_dok_titel":"Yrkesfiskets betydelse för Sveriges försörjningsförmåga","ref_dok_subtitel":"av Roland Utbult (KD)","ref_dok_subtyp":"mot","ref_dok_dokumentnamn":"Motion"},{"referenstyp":"behandlar","uppgift":"motion 2025/26:667 Husbehovsfiske som en del av samhällets krisberedskap","ref_dok_id":"HD02667","ref_dok_typ":"mot","ref_dok_rm":"2025/26","ref_dok_bet":"667","ref_dok_titel":"Husbehovsfiske som en del av samhällets krisberedskap","ref_dok_subtitel":"av Hanna Westerén (S)","ref_dok_subtyp":"mot","ref_dok_dokumentnamn":"Motion"},{"referenstyp":"behandlar","uppgift":"motion 2025/26:761 Stopp för det storskaliga fisket efter sill och strömming i Östersjön","ref_dok_id":"HD02761","ref_dok_typ":"mot","ref_dok_rm":"2025/26","ref_dok_bet":"761","ref_dok_titel":"Stopp för det storskaliga fisket efter sill och strömming i Östersjön","ref_dok_subtitel":"av Peter Hedberg m.fl. (S)","ref_dok_subtyp":"mot","ref_dok_dokumentnamn":"Motion"},{"referenstyp":"behandlar","uppgift":"motion 2025/26:794 Stärkta villkor för ett hållbart och livskraftigt svenskt fiske","ref_dok_id":"HD02794","ref_dok_typ":"mot","ref_dok_rm":"2025/26","ref_dok_bet":"794","ref_dok_titel":"Stärkta villkor för ett hållbart och livskraftigt svenskt fiske","ref_dok_subtitel":"av Magnus Berntsson (KD)","ref_dok_subtyp":"mot","ref_dok_dokumentnamn":"Motion"},{"referenstyp":"behandlar","uppgift":"motion 2025/26:808 Förbättring av förhållandena för det kustnära fisket","ref_dok_id":"HD02808","ref_dok_typ":"mot","ref_dok_rm":"2025/26","ref_dok_bet":"808","ref_dok_titel":"Förbättring av förhållandena för det kustnära fisket","ref_dok_subtitel":"av Catarina Deremar och Anne-Li Sjölund (båda C)","ref_dok_subtyp":"mot","ref_dok_dokumentnamn":"Motion"},{"referenstyp":"behandlar","uppgift":"motion 2025/26:890 Paus för sill- och strömmingsfiske i Östersjön","ref_dok_id":"HD02890","ref_dok_typ":"mot","ref_dok_rm":"2025/26","ref_dok_bet":"890","ref_dok_titel":"Paus för sill- och strömmingsfiske i Östersjön","ref_dok_subtitel":"av Magnus Manhammar (S)","ref_dok_subtyp":"mot","ref_dok_dokumentnamn":"Motion"},{"referenstyp":"behandlar","uppgift":"motion 2025/26:900 Förbud för bottentrålning i alla skyddade områden till havs","ref_dok_id":"HD02900","ref_dok_typ":"mot","ref_dok_rm":"2025/26","ref_dok_bet":"900","ref_dok_titel":"Förbud för bottentrålning i alla skyddade områden till havs","ref_dok_subtitel":"av Magnus Manhammar (S)","ref_dok_subtyp":"mot","ref_dok_dokumentnamn":"Motion"},{"referenstyp":"behandlar","uppgift":"motion 2025/26:967 Värnande av det småskaliga fisket","ref_dok_id":"HD02967","ref_dok_typ":"mot","ref_dok_rm":"2025/26","ref_dok_bet":"967","ref_dok_titel":"Värnande av det småskaliga fisket","ref_dok_subtitel":"av Daniel Persson (SD)","ref_dok_subtyp":"mot","ref_dok_dokumentnamn":"Motion"}]}}}